Workbook

Sheet Sheet1
A1: Categoria | B1: SubCategoria | C1: Sku | D1: PRODUCT NUMBER | F1: Size | G1: Precio | H1: Nombre | I1: Disponible | J1: Imagen | K1: Unidades | L1: Estado
A2: OLIVE OIL - OILS & LARD | B2: GOYA EXTRA VIRGIN OLIVE OIL | C2: 1103 | D2: 1103 | E2: =IF(C2=D2, "Same","New") -> Same | F2: 3 OZ | G2: 77.5 | H2: EXTRA VIRGIN OLIVE OIL 3 OZ | I2: =[1]Sheet1!I2 -> 1045 | J2: =C2 & "_A1C1.webp" -> 1103_A1C1.webp | K2: =Sheet4!E2 -> 36
A3: OLIVE OIL - OILS & LARD | B3: GOYA EXTRA VIRGIN OLIVE OIL | C3: 1105 | D3: 1105 | E3: =IF(C3=D3, "Same","New") -> Same | F3: 8.5 OZ | G3: 131.95 | H3: EXTRA VIRGIN OLIVE OIL 8.5 OZ | I3: =[1]Sheet1!I3 -> 3063 | J3: =C3 & "_A1C1.webp" -> 1105_A1C1.webp | K3: =Sheet4!E3 -> 25
A4: OLIVE OIL - OILS & LARD | B4: GOYA EXTRA VIRGIN OLIVE OIL | C4: 1107 | D4: 1107 | E4: =IF(C4=D4, "Same","New") -> Same | F4: 17 OZ | G4: 120.5 | H4: EXTRA VIRGIN OLIVE OIL 17 OZ | I4: =[1]Sheet1!I4 -> 3740 | J4: =C4 & "_A1C1.webp" -> 1107_A1C1.webp | K4: =Sheet4!E4 -> 12
A5: OLIVE OIL - OILS & LARD | B5: GOYA EXTRA VIRGIN OLIVE OIL | C5: 1108 | D5: 1108 | E5: =IF(C5=D5, "Same","New") -> Same | F5: 25.4 OZ | G5: 134.95 | H5: EXTRA VIRGIN OLIVE OIL 25.4 OZ | I5: =[1]Sheet1!I5 -> 243 | J5: =C5 & "_A1C1.webp" -> 1108_A1C1.webp | K5: =Sheet4!E5 -> 9
A6: OLIVE OIL - OILS & LARD | B6: GOYA EXTRA VIRGIN OLIVE OIL | C6: 1109 | D6: 1109 | E6: =IF(C6=D6, "Same","New") -> Same | F6: 34 OZ | G6: 169.95 | H6: EXTRA VIRGIN OLIVE OIL 34 OZ | I6: =[1]Sheet1!I6 -> 1434 | J6: =C6 & "_A1C1.webp" -> 1109_A1C1.webp | K6: =Sheet4!E6 -> 9
A7: OLIVE OIL - OILS & LARD | B7: GOYA EXTRA VIRGIN OLIVE OIL | C7: 1111 | D7: 1111 | E7: =IF(C7=D7, "Same","New") -> Same | F7: 50.7 OZ | G7: 168.95 | H7: EXTRA VIRGIN OLIVE OIL 50.7 OZ | I7: =[1]Sheet1!I7 -> 134 | J7: =C7 & "_A1C1.webp" -> 1111_A1C1.webp | K7: =Sheet4!E7 -> 6
A8: OLIVE OIL - OILS & LARD | B8: GOYA EXTRA VIRGIN OLIVE OIL | C8: 1120 | D8: 1120 | E8: =IF(C8=D8, "Same","New") -> Same | F8: 24 OZ | G8: 171.95 | H8: EXTRA VIRGIN OLIVE OIL 24 OZ | I8: =[1]Sheet1!I8 -> 3 | J8: =C8 & "_A1C1.webp" -> 1120_A1C1.webp | K8: =Sheet4!E8 -> 12
A9: OLIVE OIL - OILS & LARD | B9: GOYA EXTRA VIRGIN OLIVE OIL | C9: 1128 | D9: 1128 | E9: =IF(C9=D9, "Same","New") -> Same | F9: 102 OZ | G9: 170.5 | H9: EXTRA VIRGIN OLIVE OIL 3 LTS | I9: =[1]Sheet1!I9 -> 78 | J9: =C9 & "_A1C1.webp" -> 1128_A1C1.webp | K9: =Sheet4!E9 -> 3
A10: OLIVE OIL - OILS & LARD | B10: GOYA EXTRA VIRGIN OLIVE OIL | C10: 1130 | D10: 1130 | E10: =IF(C10=D10, "Same","New") -> Same | F10: 17 OZ | G10: 144.95 | H10: GOYA UNICO XTRA VIRGIN OLV OIL | I10: =[1]Sheet1!I10 -> 67 | J10: =C10 & "_A1C1.webp" -> 1130_A1C1.webp | K10: =Sheet4!E10 -> 12
A11: OLIVE OIL - OILS & LARD | B11: GOYA EXTRA VIRGIN OLIVE OIL | C11: 1133 | D11: 1133 | E11: =IF(C11=D11, "Same","New") -> Same | F11: 17 OZ | G11: 135.35 | H11: ORGANIC EXTRA VIRGIN OLIVE OIL | I11: =[1]Sheet1!I11 -> 124 | J11: =C11 & "_A1C1.webp" -> 1133_A1C1.webp | K11: =Sheet4!E11 -> 12
A12: OLIVE OIL - OILS & LARD | B12: GOYA OLIVE OIL | C12: 1141 | D12: 1141 | E12: =IF(C12=D12, "Same","New") -> Same | F12: 8.5 OZ | G12: 113.5 | H12: PURO OLIVE OIL 8.5 OZ | I12: =[1]Sheet1!I12 -> 495 | J12: =C12 & "_A1C1.webp" -> 1141_A1C1.webp | K12: =Sheet4!E12 -> 25
A13: OLIVE OIL - OILS & LARD | B13: GOYA OLIVE OIL | C13: 1142 | D13: 1142 | E13: =IF(C13=D13, "Same","New") -> Same | F13: 17 OZ | G13: 103.95 | H13: PURO OLIVE OIL 17 OZ | I13: =[1]Sheet1!I13 -> 436 | J13: =C13 & "_A1C1.webp" -> 1142_A1C1.webp | K13: =Sheet4!E13 -> 12
... A19: OLIVE OIL - OILS & LARD | B19: OLE-O OLIVE OIL BLEND | C19: 1186 | D19: 1186 | E19: =IF(C19=D19, "Same","New") -> Same | F19: 50.7 OZ | G19: 91.5 | H19: OLE-O OLIVE OIL BLEND | I19: =[1]Sheet1!I19 -> 327 | J19: =C19 & "_A1C1.webp" -> 1186_A1C1.webp | K19: =Sheet4!E19 -> 6
A20: OLIVE OIL - OILS & LARD | B20: GOYA EXTRA VIRGIN OLIVE OIL WITH TRUFFLE FLAVOR | C20: 1188 | D20: 1188 | E20: =IF(C20=D20, "Same","New") -> Same | F20: 8.5 OZ | G20: 76.95 | H20: EV OLIVE OIL TRUFFLE FLV | I20: =[1]Sheet1!I20 -> 83 | J20: =C20 & "_A1C1.webp" -> 1188_A1C1.webp | K20: =Sheet4!E20 -> 12 | L20: New
A21: MARINADES - VINEGAR & WINE | B21: GOYA VINEGAR | C21: 1190 | D21: 1190 | E21: =IF(C21=D21, "Same","New") -> Same | F21: 8.5 OZ | G21: 26.5 | H21: VINEGAR BALSAMIC 8.50 OZ. | I21: =[1]Sheet1!I21 -> 168 | J21: =C21 & "_A1C1.webp" -> 1190_A1C1.webp | K21: =Sheet4!E21 -> 9
A22: MARINADES - VINEGAR & WINE | B22: GOYA VINEGAR | C22: 1191 | D22: 1191 | E22: =IF(C22=D22, "Same","New") -> Same | F22: 8.5 OZ | G22: 24.5 | H22: SHERRY VINEGAR 8.50 OZ. | I22: =[1]Sheet1!I22 -> 28 | J22: =C22 & "_A1C1.webp" -> 1191_A1C1.webp | K22: =Sheet4!E22 -> 9
A23: MARINADES - VINEGAR & WINE | B23: GOYA VINEGAR | C23: 1192 | D23: 1192 | E23: =IF(C23=D23, "Same","New") -> Same | F23: 8.5 OZ | G23: 29.95 | H23: SHERRY VINEGAR RESERVA 8.50 OZ | I23: =[1]Sheet1!I23 -> 32 | J23: =C23 & "_A1C1.webp" -> 1192_A1C1.webp | K23: =Sheet4!E23 -> 9
A24: OLIVE OIL - OILS & LARD | B24: GOYA EXTRA VIRGIN OLIVE OIL WITH GARLIC FLAVOR | C24: 1195 | D24: 1195 | E24: =IF(C24=D24, "Same","New") -> Same | F24: 8.5 OZ | G24: 76.95 | H24: GARLIC EXTRA VIRGIN OLIVE OIL | I24: =[1]Sheet1!I24 -> 251 | J24: =C24 & "_A1C1.webp" -> 1195_A1C1.webp | K24: =Sheet4!E24 -> 12
A25: OLIVE OIL - OILS & LARD | B25: GOYA EXTRA VIRGIN OLIVE OIL SPRAY | C25: 1199 | D25: 1199 | E25: =IF(C25=D25, "Same","New") -> Same | F25: 5 OZ | G25: 43.5 | H25: EXTRA VIRGIN OLIVE OIL SPRAY | I25: =[1]Sheet1!I25 -> 550 | J25: =C25 & "_A1C1.webp" -> 1199_A1C1.webp | K25: =Sheet4!E25 -> 12 | L25: New
A26: OLIVE OIL - OILS & LARD | B26: GOYA COOKING OILS & LARD | C26: 1222 | D26: 1222 | E26: =IF(C26=D26, "Same","New") -> Same | F26: 280 OZ | G26: 61.5 | H26: PURE CORN OIL 280 OZ | I26: =[1]Sheet1!I26 -> 155 | J26: =C26 & "_A1C1.webp" -> 1222_A1C1.webp | K26: =Sheet4!E26 -> 2
A27: OLIVE OIL - OILS & LARD | B27: GOYA COOKING OILS & LARD | C27: 1227 | D27: 1227 | E27: =IF(C27=D27, "Same","New") -> Same | F27: 16 OZ | G27: 47.5 | H27: PURE CORN OIL 16 OZ | I27: =[1]Sheet1!I27 -> 526 | J27: =C27 & "_A1C1.webp" -> 1227_A1C1.webp | K27: =Sheet4!E27 -> 24
A28: OLIVE OIL - OILS & LARD | B28: GOYA COOKING OILS & LARD | C28: 1229 | D28: 1229 | E28: =IF(C28=D28, "Same","New") -> Same | F28: 24 OZ | G28: 34.5 | H28: PURE CORN OIL 24 OZ | I28: =[1]Sheet1!I28 -> 917 | J28: =C28 & "_A1C1.webp" -> 1229_A1C1.webp | K28: =Sheet4!E28 -> 12
A29: OLIVE OIL - OILS & LARD | B29: GOYA COOKING OILS & LARD | C29: 1231 | D29: 1231 | E29: =IF(C29=D29, "Same","New") -> Same | F29: 48 OZ | G29: 45.5 | H29: PURE CORN OIL 48 OZ | I29: =[1]Sheet1!I29 -> 703 | J29: =C29 & "_A1C1.webp" -> 1231_A1C1.webp | K29: =Sheet4!E29 -> 9
A30: OLIVE OIL - OILS & LARD | B30: GOYA COOKING OILS & LARD | C30: 1233 | D30: 1233 | E30: =IF(C30=D30, "Same","New") -> Same | F30: 128 OZ | G30: 74.5 | H30: PURE CORN OIL 1 GAL | I30: =[1]Sheet1!I30 -> 164 | J30: =C30 & "_A1C1.webp" -> 1233_A1C1.webp | K30: =Sheet4!E30 -> 6
A31: OLIVE OIL - OILS & LARD | B31: GOYA COOKING OILS & LARD | C31: 1234 | D31: 1234 | E31: =IF(C31=D31, "Same","New") -> Same | F31: 96 OZ | G31: 59.95 | H31: PURE CORN OIL 96 OZ | I31: =[1]Sheet1!I31 -> 412 | J31: =C31 & "_A1C1.webp" -> 1234_A1C1.webp | K31: =Sheet4!E31 -> 6
A32: OLIVE OIL - OILS & LARD | B32: GOYA COOKING OILS & LARD | C32: 1235 | D32: 1235 | E32: =IF(C32=D32, "Same","New") -> Same | F32: 16 OZ | G32: 42.95 | H32: VEGETABLE OIL 16 OZ | I32: =[1]Sheet1!I32 -> 610 | J32: =C32 & "_A1C1.webp" -> 1235_A1C1.webp | K32: =Sheet4!E32 -> 24
A33: OLIVE OIL - OILS & LARD | B33: GOYA COOKING OILS & LARD | C33: 1237 | D33: 1237 | E33: =IF(C33=D33, "Same","New") -> Same | F33: 24 OZ | G33: 30.5 | H33: VEGETABLE OIL 24 OZ | I33: =[1]Sheet1!I33 -> 1080 | J33: =C33 & "_A1C1.webp" -> 1237_A1C1.webp | K33: =Sheet4!E33 -> 12
A34: OLIVE OIL - OILS & LARD | B34: GOYA COOKING OILS & LARD | C34: 1239 | D34: 1239 | E34: =IF(C34=D34, "Same","New") -> Same | F34: 48 OZ | G34: 40.5 | H34: VEGETABLE OIL 48 OZ | I34: =[1]Sheet1!I34 -> 972 | J34: =C34 & "_A1C1.webp" -> 1239_A1C1.webp | K34: =Sheet4!E34 -> 9
A35: OLIVE OIL - OILS & LARD | B35: GOYA COOKING OILS & LARD | C35: 1240 | D35: 1240 | E35: =IF(C35=D35, "Same","New") -> Same | F35: 96 OZ | G35: 53.95 | H35: VEGETABLE OIL 96 OZ | I35: =[1]Sheet1!I35 -> 163 | J35: =C35 & "_A1C1.webp" -> 1240_A1C1.webp | K35: =Sheet4!E35 -> 6
A36: OLIVE OIL - OILS & LARD | B36: GOYA COOKING OILS & LARD | C36: 1241 | D36: 1241 | E36: =IF(C36=D36, "Same","New") -> Same | F36: 128 OZ | G36: 66.5 | H36: VEGETABLE OIL 1 GAL | I36: =[1]Sheet1!I36 -> 411 | J36: =C36 & "_A1C1.webp" -> 1241_A1C1.webp | K36: =Sheet4!E36 -> 6
A37: OLIVE OIL - OILS & LARD | B37: GOYA COOKING OILS & LARD | C37: 1250 | D37: 1250 | E37: =IF(C37=D37, "Same","New") -> Same | F37: 48 OZ | G37: 39.95 | H37: CANOLA OIL 48 OZ | I37: =[1]Sheet1!I37 -> 233 | J37: =C37 & "_A1C1.webp" -> 1250_A1C1.webp | K37: =Sheet4!E37 -> 9
A38: OLIVE OIL - OILS & LARD | B38: GOYA COOKING OILS & LARD | C38: 1251 | D38: 1251 | E38: =IF(C38=D38, "Same","New") -> Same | F38: 96 OZ | G38: 53.5 | H38: CANOLA OIL 96 OZ | I38: =[1]Sheet1!I38 -> 166 | J38: =C38 & "_A1C1.webp" -> 1251_A1C1.webp | K38: =Sheet4!E38 -> 6
A39: OLIVE OIL - OILS & LARD | B39: GOYA AVOCADO OIL | C39: 1255 | D39: 1255 | E39: =IF(C39=D39, "Same","New") -> Same | F39: 25.4 OZ | G39: 55.95 | H39: GOYA AVOCADO OIL 25.4 OZ | I39: =[1]Sheet1!I39 -> 1608 | J39: =C39 & "_A1C1.webp" -> 1255_A1C1.webp | K39: =Sheet4!E39 -> 6 | L39: New
A40: OLIVES & PICKLED PRODUCTS/ OLIVES | B40: PERDIGON/ MANZANILLA COCKTAIL OLIVES | C40: 1304 | D40: 1304 | E40: =IF(C40=D40, "Same","New") -> Same | F40: 9.5 OZ | G40: 18.95 | H40: PERDIGON OLIVES 12/9.5 OZ | I40: =[1]Sheet1!I40 -> 63 | J40: =C40 & "_A1C1.webp" -> 1304_A1C1.webp | K40: =Sheet4!E40 -> 12
A41: OLIVES & PICKLED PRODUCTS/ OLIVES | B41: GOYA JAR/ MANZANILLA OLIVES | C41: 1307 | D41: 1307 | E41: =IF(C41=D41, "Same","New") -> Same | F41: 3.75 OZ | G41: 16.95 | H41: MANZANILLA OLIVES | I41: =[1]Sheet1!I41 -> 374 | J41: =C41 & "_A1C1.webp" -> 1307_A1C1.webp | K41: =Sheet4!E41 -> 12
A42: OLIVES & PICKLED PRODUCTS/ OLIVES | B42: GOYA JAR/ MANZANILLA OLIVES | C42: 1309 | D42: 1309 | E42: =IF(C42=D42, "Same","New") -> Same | F42: 9.5 OZ | G42: 27.25 | H42: MANZANILLA OLIVES 9.5 OZ | I42: =[1]Sheet1!I42 -> 662 | J42: =C42 & "_A1C1.webp" -> 1309_A1C1.webp | K42: =Sheet4!E42 -> 12
A43: OLIVES & PICKLED PRODUCTS/ OLIVES | B43: PERDIGON/ MANZANILLA COCKTAIL OLIVES | C43: 1312 | D43: 1312 | E43: =IF(C43=D43, "Same","New") -> Same | F43: 20 OZ | G43: 36.25 | H43: PERDIGON OLIVES 20 OZ | I43: =[1]Sheet1!I43 -> 322 | J43: =C43 & "_A1C1.webp" -> 1312_A1C1.webp | K43: =Sheet4!E43 -> 12
A44: OLIVES & PICKLED PRODUCTS/ OLIVES | B44: PERDIGON/ MANZANILLA COCKTAIL OLIVES | C44: 1317 | D44: 1317 | E44: =IF(C44=D44, "Same","New") -> Same | F44: 2.25 OZ | G44: 14.25 | H44: COCKTAIL PITTED OLIVES | I44: =[1]Sheet1!I44 -> 187 | J44: =C44 & "_A1C1.webp" -> 1317_A1C1.webp | K44: =Sheet4!E44 -> 12
A45: OLIVES & PICKLED PRODUCTS/ OLIVES | B45: PERDIGON/ MANZANILLA COCKTAIL OLIVES | C45: 1319 | D45: 1319 | E45: =IF(C45=D45, "Same","New") -> Same | F45: 5.5 OZ | G45: 41.75 | H45: COCKTAIL PITTED OLIVES 5.5 OZ | I45: =[1]Sheet1!I45 -> 1851 | J45: =C45 & "_A1C1.webp" -> 1319_A1C1.webp | K45: =Sheet4!E45 -> 24
A46: OLIVES & PICKLED PRODUCTS/ OLIVES | B46: GOYA JAR/ MANZANILLA OLIVES STUFFED WITH MINCED PIMIENTOS | C46: 1327 | D46: 1327 | E46: =IF(C46=D46, "Same","New") -> Same | F46: 3.75 OZ | G46: 18.95 | H46: STUFF MANZANILLA OLIVES | I46: =[1]Sheet1!I46 -> 716 | J46: =C46 & "_A1C1.webp" -> 1327_A1C1.webp | K46: =Sheet4!E46 -> 12
A47: OLIVES & PICKLED PRODUCTS/ OLIVES | B47: GOYA JAR/ MANZANILLA OLIVES STUFFED WITH MINCED PIMIENTOS | C47: 1331 | D47: 1331 | E47: =IF(C47=D47, "Same","New") -> Same | F47: 9.5 OZ | G47: 31.5 | H47: STUFF MANZANILLA OLIVES 9.5 OZ | I47: =[1]Sheet1!I47 -> 2230 | J47: =C47 & "_A1C1.webp" -> 1331_A1C1.webp | K47: =Sheet4!E47 -> 12
A48: OLIVES & PICKLED PRODUCTS/ OLIVES | B48: GOYA JAR/ MANZANILLA OLIVES STUFFED WITH MINCED PIMIENTOS | C48: 1332 | D48: 1332 | E48: =IF(C48=D48, "Same","New") -> Same | F48: 20 OZ | G48: 64.5 | H48: STUFF MANZANILLA OLIVES 20 OZ | I48: =[1]Sheet1!I48 -> 438 | J48: =C48 & "_A1C1.webp" -> 1332_A1C1.webp | K48: =Sheet4!E48 -> 12
A49: OLIVES & PICKLED PRODUCTS/ OLIVES | B49: GOYA JAR/ QUEEN OLIVES & JUMBO STUFFED WITH MINCED PIMIENTOS | C49: 1333 | D49: 1333 | E49: =IF(C49=D49, "Same","New") -> Same | F49: 3.375 OZ | G49: 21.5 | H49: STUFFED QUEEN OLIVES | I49: =[1]Sheet1!I49 -> 111 | J49: =C49 & "_A1C1.webp" -> 1333_A1C1.webp | K49: =Sheet4!E49 -> 12
A50: OLIVES & PICKLED PRODUCTS/ OLIVES | B50: GOYA JAR/ QUEEN OLIVES & JUMBO STUFFED WITH MINCED PIMIENTOS | C50: 1335 | D50: 1335 | E50: =IF(C50=D50, "Same","New") -> Same | F50: 9 OZ | G50: 41.5 | H50: STUFFED QUEEN OLIVES 9 OZ | I50: =[1]Sheet1!I50 -> 243 | J50: =C50 & "_A1C1.webp" -> 1335_A1C1.webp | K50: =Sheet4!E50 -> 12
A51: OLIVES & PICKLED PRODUCTS/ OLIVES | B51: GOYA JAR/ QUEEN OLIVES & JUMBO STUFFED WITH MINCED PIMIENTOS | C51: 1337 | D51: 1337 | E51: =IF(C51=D51, "Same","New") -> Same | F51: 20 OZ | G51: 86.95 | H51: STUFF QUEEN OLIV W/MINCED PIM | I51: =[1]Sheet1!I51 -> 183 | J51: =C51 & "_A1C1.webp" -> 1337_A1C1.webp | K51: =Sheet4!E51 -> 12
A52: OLIVES & PICKLED PRODUCTS/ OLIVES | B52: GOYA JAR/ MANZANILLA OLIVES STUFFED WITH MINCED PIMIENTOS | C52: 1341 | D52: 1341 | E52: =IF(C52=D52, "Same","New") -> Same | F52: 5.75 OZ | G52: 18.95 | H52: GOYA MANZANILLAS RELLENAS | I52: =[1]Sheet1!I52 -> 845 | J52: =C52 & "_A1C1.webp" -> 1341_A1C1.webp | K52: =Sheet4!E52 -> 12
A53: OLIVES & PICKLED PRODUCTS/ OLIVES | B53: GOYA ORGANIC OLIVES & CAPERS | C53: 1345 | D53: 1345 | E53: =IF(C53=D53, "Same","New") -> Same | F53: 5.5 OZ | G53: 23.5 | H53: GOYA ORGANICS COCKTAIL OLIVES | I53: =[1]Sheet1!I53 -> 222 | J53: =C53 & "_A1C1.webp" -> 1345_A1C1.webp | K53: =Sheet4!E53 -> 12 | L53: New
A54: OLIVES & PICKLED PRODUCTS/ OLIVES | B54: GOYA ORGANIC OLIVES & CAPERS | C54: 1346 | D54: 1346 | E54: =IF(C54=D54, "Same","New") -> Same | F54: 6.75 OZ | G54: 24.95 | H54: GOYA ORGANICS MANZANILLA OLIVE | I54: =[1]Sheet1!I54 -> 51 | J54: =C54 & "_A1C1.webp" -> 1346_A1C1.webp | K54: =Sheet4!E54 -> 12 | L54: New
A55: OLIVES & PICKLED PRODUCTS/ OLIVES | B55: GOYA JAR/ QUEEN OLIVES & JUMBO SALAD OLIVES | C55: 1351 | D55: 1351 | E55: =IF(C55=D55, "Same","New") -> Same | F55: 3.375 OZ | G55: 19.95 | H55: JUMBO OLIVES | I55: =[1]Sheet1!I55 -> 59 | J55: =C55 & "_A1C1.webp" -> 1351_A1C1.webp | K55: =Sheet4!E55 -> 12
A56: OLIVES & PICKLED PRODUCTS/ OLIVES | B56: GOYA JAR/ QUEEN OLIVES & JUMBO SALAD OLIVES | C56: 1353 | D56: 1353 | E56: =IF(C56=D56, "Same","New") -> Same | F56: 9.5 OZ | G56: 32.95 | H56: JUMBO OLIVES 9.5 OZ | I56: =[1]Sheet1!I56 -> 396 | J56: =C56 & "_A1C1.webp" -> 1353_A1C1.webp | K56: =Sheet4!E56 -> 12
A57: OLIVES & PICKLED PRODUCTS/ OLIVES | B57: GOYA ORGANIC OLIVES & CAPERS | C57: 1360 | D57: 1360 | E57: =IF(C57=D57, "Same","New") -> Same | F57: 2.5 OZ | G57: 37.5 | H57: GOYA ORGANICS CAPERS 2.5 OZ | I57: =[1]Sheet1!I57 -> 12 | J57: =C57 & "_A1C1.webp" -> 1360_A1C1.webp | K57: =Sheet4!E57 -> 12
A58: OLIVES & PICKLED PRODUCTS/ OLIVES | B58: GOYA ORGANIC OLIVES & CAPERS | C58: 1363 | D58: 1363 | E58: =IF(C58=D58, "Same","New") -> Same | F58: 2.5 OZ | G58: 30.95 | H58: GOYA ORGANICS CAPERS CAPOTES | I58: =[1]Sheet1!I58 -> 37 | J58: =C58 & "_A1C1.webp" -> 1363_A1C1.webp | K58: =Sheet4!E58 -> 12
A59: OLIVES & PICKLED PRODUCTS/ OLIVES | B59: GOYA CAPERS | C59: 1368 | D59: 1368 | E59: =IF(C59=D59, "Same","New") -> Same | F59: 2 OZ | G59: 25.95 | H59: REDUCED SODIUM CAPERS CAPOTES | I59: =[1]Sheet1!I59 -> 57 | J59: =C59 & "_A1C1.webp" -> 1368_A1C1.webp | K59: =Sheet4!E59 -> 12
A60: OLIVES & PICKLED PRODUCTS/ OLIVES | B60: GOYA CAPERS | C60: 1370 | D60: 1370 | E60: =IF(C60=D60, "Same","New") -> Same | F60: 2.5 OZ | G60: 30.95 | H60: SPAN NONPAREILS-CAPERS 2.5 OZ | I60: =[1]Sheet1!I60 -> 880 | J60: =C60 & "_A1C1.webp" -> 1370_A1C1.webp | K60: =Sheet4!E60 -> 12
A61: OLIVES & PICKLED PRODUCTS/ OLIVES | B61: GOYA CAPERS | C61: 1373 | D61: 1373 | E61: =IF(C61=D61, "Same","New") -> Same | F61: 2.25 OZ | G61: 26.5 | H61: SPANISH CAPERS - ALCAPARR | I61: =[1]Sheet1!I61 -> 813 | J61: =C61 & "_A1C1.webp" -> 1373_A1C1.webp | K61: =Sheet4!E61 -> 12
A62: OLIVES & PICKLED PRODUCTS/ OLIVES | B62: GOYA CAPERS | C62: 1375 | D62: 1375 | E62: =IF(C62=D62, "Same","New") -> Same | F62: 3.25 OZ | G62: 32.95 | H62: SPANISH CAPERS-ALCAPARR 3.25OZ | I62: =[1]Sheet1!I62 -> 1166 | J62: =C62 & "_A1C1.webp" -> 1375_A1C1.webp | K62: =Sheet4!E62 -> 12
A63: OLIVES & PICKLED PRODUCTS/ OLIVES | B63: GOYA CAPERS | C63: 1377 | D63: 1377 | E63: =IF(C63=D63, "Same","New") -> Same | F63: 4.25 OZ | G63: 41.95 | H63: SPANISH CAPERS-ALCAPARR 4.25OZ | I63: =[1]Sheet1!I63 -> 210 | J63: =C63 & "_A1C1.webp" -> 1377_A1C1.webp | K63: =Sheet4!E63 -> 12
A64: OLIVES & PICKLED PRODUCTS/ OLIVES | B64: GOYA JAR/ ALCAPARRADO | C64: 1417 | D64: 1417 | E64: =IF(C64=D64, "Same","New") -> Same | F64: 7 OZ | G64: 47.95 | H64: ALCAPARRADO PITTED 7 OZ | I64: =[1]Sheet1!I64 -> 1746 | J64: =C64 & "_A1C1.webp" -> 1417_A1C1.webp | K64: =Sheet4!E64 -> 24
A65: OLIVES & PICKLED PRODUCTS/ OLIVES | B65: GOYA JAR/ ALCAPARRADO | C65: 1419 | D65: 1419 | E65: =IF(C65=D65, "Same","New") -> Same | F65: 9.5 OZ | G65: 30.75 | H65: ALCAPARRADO PITTED 9.5 OZ | I65: =[1]Sheet1!I65 -> 2749 | J65: =C65 & "_A1C1.webp" -> 1419_A1C1.webp | K65: =Sheet4!E65 -> 12
A66: OLIVES & PICKLED PRODUCTS/ OLIVES | B66: GOYA JAR/ ALCAPARRADO | C66: 1421 | D66: 1421 | E66: =IF(C66=D66, "Same","New") -> Same | F66: 19.25 OZ | G66: 58.95 | H66: GOYA ALCAPARRADO PITTED | I66: =[1]Sheet1!I66 -> 625 | J66: =C66 & "_A1C1.webp" -> 1421_A1C1.webp | K66: =Sheet4!E66 -> 12
... A146: SOUPS AND BLENDS | B146: GOYA CARRIBEAN STYLE - SOUP & STEWS | C146: 2131 | D146: 2131 | E146: =IF(C146=D146, "Same","New") -> Same | F146: 15 OZ | G146: 41.5 | H146: SANCOCHO 15 OZ | I146: =[1]Sheet1!I146 -> 0 | J146: =C146 & "_A1C1.webp" -> 2131_A1C1.webp | K146: =Sheet4!E146 -> 24
A147: COCONUT & MILK PRODUCTS | B147: GOYA COCONUT MILK | C147: 2132 | D147: 2132 | E147: =IF(C147=D147, "Same","New") -> Same | F147: 13.5 OZ | G147: 49.95 | H147: GOYA ORGANIC COCONUT MILK | I147: =[1]Sheet1!I147 -> 0 | J147: =C147 & "_A1C1.webp" -> 2132_A1C1.webp | K147: =Sheet4!E147 -> 24 | L147: New
A148: SOUPS AND BLENDS | B148: GOYA CARRIBEAN STYLE - SOUP & STEWS | C148: 2133 | D148: 2133 | E148: =IF(C148=D148, "Same","New") -> Same | F148: 15 OZ | G148: 77.95 | H148: MONDONGO 15 OZ | I148: =[1]Sheet1!I148 -> 41 | J148: =C148 & "_A1C1.webp" -> 2133_A1C1.webp | K148: =Sheet4!E148 -> 24
A149: SOUPS AND BLENDS | B149: GOYA CARRIBEAN STYLE - SOUP & STEWS | C149: 2138 | D149: 2138 | E149: =IF(C149=D149, "Same","New") -> Same | F149: 15 OZ | G149: 77.95 | H149: MONDONGO DOMINICANO 15 OZ | I149: =[1]Sheet1!I149 -> 8 | J149: =C149 & "_A1C1.webp" -> 2138_A1C1.webp | K149: =Sheet4!E149 -> 24
A150: COOKING BASES AND SAUCES | B150: GOYA KETCHUP - MAYONNAISE - CHIMICHURRI | C150: 2145 | D150: 2145 | E150: =IF(C150=D150, "Same","New") -> Same | F150: 7.5 OZ | G150: 42.95 | H150: CHIMICHURRI STEAK SAUCE 12/7.5 | I150: =[1]Sheet1!I150 -> 6 | J150: =C150 & "_A1C1.webp" -> 2145_A1C1.webp | K150: =Sheet4!E150 -> 12
A151: COOKING BASES AND SAUCES | B151: GOYA SOFRITO | C151: 2146 | D151: 2146 | E151: =IF(C151=D151, "Same","New") -> Same | F151: 12 OZ | G151: 47.95 | H151: SOFRITO 12 OZ | I151: =[1]Sheet1!I151 -> 8127 | J151: =C151 & "_A1C1.webp" -> 2146_A1C1.webp | K151: =Sheet4!E151 -> 24
A152: COOKING BASES AND SAUCES | B152: GOYA SOFRITO | C152: 2148 | D152: 2148 | E152: =IF(C152=D152, "Same","New") -> Same | F152: 6 OZ | G152: 32.95 | H152: SOFRITO 6 OZ | I152: =[1]Sheet1!I152 -> 2206 | J152: =C152 & "_A1C1.webp" -> 2148_A1C1.webp | K152: =Sheet4!E152 -> 24
A153: COOKING BASES AND SAUCES | B153: GOYA SOFRITO | C153: 2149 | D153: 2149 | E153: =IF(C153=D153, "Same","New") -> Same | F153: 24 OZ | G153: 46.95 | H153: SOFRITO 24 OZ | I153: =[1]Sheet1!I153 -> 1989 | J153: =C153 & "_A1C1.webp" -> 2149_A1C1.webp | K153: =Sheet4!E153 -> 12
A154: COOKING BASES AND SAUCES | B154: GOYA RECAITO | C154: 2150 | D154: 2150 | E154: =IF(C154=D154, "Same","New") -> Same | F154: 24 OZ | G154: 46.95 | H154: RECAITO 24 OZ | I154: =[1]Sheet1!I154 -> 967 | J154: =C154 & "_A1C1.webp" -> 2150_A1C1.webp | K154: =Sheet4!E154 -> 12
A155: COOKING BASES AND SAUCES | B155: GOYA RECAITO | C155: 2151 | D155: 2151 | E155: =IF(C155=D155, "Same","New") -> Same | F155: 6 OZ | G155: 32.95 | H155: RECAITO 6 OZ | I155: =[1]Sheet1!I155 -> 1101 | J155: =C155 & "_A1C1.webp" -> 2151_A1C1.webp | K155: =Sheet4!E155 -> 24
A156: COOKING BASES AND SAUCES | B156: GOYA RECAITO | C156: 2152 | D156: 2152 | E156: =IF(C156=D156, "Same","New") -> Same | F156: 12 OZ | G156: 47.95 | H156: RECAITO 12 OZ | I156: =[1]Sheet1!I156 -> 1475 | J156: =C156 & "_A1C1.webp" -> 2152_A1C1.webp | K156: =Sheet4!E156 -> 24
A157: COOKING BASES AND SAUCES | B157: GOYA SAZON LIQUIDO | C157: 2153 | D157: 2153 | E157: =IF(C157=D157, "Same","New") -> Same | F157: 15 OZ | G157: 34.5 | H157: GOYA LIQUIDO SZN 15 OZ | I157: =[1]Sheet1!I157 -> 89 | J157: =C157 & "_A1C1.webp" -> 2153_A1C1.webp | K157: =Sheet4!E157 -> 24
A158: COOKING BASES AND SAUCES | B158: GOYA SAZON LIQUIDO | C158: 2154 | D158: 2154 | E158: =IF(C158=D158, "Same","New") -> Same | F158: 30 OZ | G158: 31.95 | H158: GOYA LIQUIDO SZN 30 OZ | I158: =[1]Sheet1!I158 -> 477 | J158: =C158 & "_A1C1.webp" -> 2154_A1C1.webp | K158: =Sheet4!E158 -> 12
A159: COCONUT & MILK PRODUCTS | B159: GOYA PIÑA COLADA | C159: 2159 | D159: 2159 | E159: =IF(C159=D159, "Same","New") -> Same | F159: 12 OZ | G159: 36.95 | H159: PINA COLADA MIX 12 OZ | I159: =[1]Sheet1!I159 -> 285 | J159: =C159 & "_A1C1.webp" -> 2159_A1C1.webp | K159: =Sheet4!E159 -> 24
A160: COCONUT & MILK PRODUCTS | B160: GOYA CREAM OF COCONUT | C160: 2161 | D160: 2161 | E160: =IF(C160=D160, "Same","New") -> Same | F160: 8.75 OZ | G160: 36.95 | H160: COCO GOYA 8 3/4 OZ | I160: =[1]Sheet1!I160 -> 44 | J160: =C160 & "_A1C1.webp" -> 2161_A1C1.webp | K160: =Sheet4!E160 -> 24
A161: COCONUT & MILK PRODUCTS | B161: GOYA CREAM OF COCONUT | C161: 2162 | D161: 2162 | E161: =IF(C161=D161, "Same","New") -> Same | F161: 50 OZ | H161: GOYA CREAM OF COCONUT 12/50 OZ | I161: =[1]Sheet1!I161 -> 0 | J161: =C161 & "_A1C1.webp" -> 2162_A1C1.webp | K161: =Sheet4!E161 -> 12 | L161: New
A162: COCONUT & MILK PRODUCTS | B162: GOYA CREAM OF COCONUT | C162: 2163 | D162: 2163 | E162: =IF(C162=D162, "Same","New") -> Same | F162: 15 OZ | G162: 47.95 | H162: COCO GOYA CREAM OF COCONUT | I162: =[1]Sheet1!I162 -> 3315 | J162: =C162 & "_A1C1.webp" -> 2163_A1C1.webp | K162: =Sheet4!E162 -> 24
A163: COCONUT & MILK PRODUCTS | B163: GOYA COCONUT MILK | C163: 2164 | D163: 2164 | E163: =IF(C163=D163, "Same","New") -> Same | F163: 13.5 OZ | G163: 42.95 | H163: COCONUT MILK 13.5 OZ | I163: =[1]Sheet1!I163 -> 28545 | J163: =C163 & "_A1C1.webp" -> 2164_A1C1.webp | K163: =Sheet4!E163 -> 24
A164: COCONUT & MILK PRODUCTS | B164: GOYA COCONUT MILK | C164: 2165 | D164: 2165 | E164: =IF(C164=D164, "Same","New") -> Same | F164: 13.5 OZ | G164: 42.95 | H164: GOYA COCONUT MILK LIGHT | I164: =[1]Sheet1!I164 -> 1661 | J164: =C164 & "_A1C1.webp" -> 2165_A1C1.webp | K164: =Sheet4!E164 -> 24
A165: SHIPPERS AND DISPLAYS | B165: COCONUT & MILK PRODUCTS | C165: 2166 | D165: 2166 | E165: =IF(C165=D165, "Same","New") -> Same | F165: 15 OZ | G165: 95.5 | H165: CREAM OF COCONUT SHIPPER | I165: =[1]Sheet1!I165 -> 1177 | J165: =C165 & "_A1C1.webp" -> 2166_A1C1.webp | K165: =Sheet4!E165 -> 48
A166: COCONUT & MILK PRODUCTS | B166: GOYA COCONUT MILK | C166: 2168 | D166: 2168 | E166: =IF(C166=D166, "Same","New") -> Same | F166: 25.5 OZ | G166: 42.5 | H166: COCONUT MILK 25.5 OZ | I166: =[1]Sheet1!I166 -> 4136 | J166: =C166 & "_A1C1.webp" -> 2168_A1C1.webp | K166: =Sheet4!E166 -> 12
A167: DESSERTS | B167: GOYA DESSERTS | C167: 2169 | D167: 2169 | E167: =IF(C167=D167, "Same","New") -> Same | F167: 15.5 OZ | G167: 36.95 | H167: HABICHUELAS CON DULCE 24/15.5 | I167: =[1]Sheet1!I167 -> 368 | J167: =C167 & "_A1C1.webp" -> 2169_A1C1.webp | K167: =Sheet4!E167 -> 24
A168: COCONUT & MILK PRODUCTS | B168: GOYA COCONUT MILK | C168: 2171 | D168: 2171 | E168: =IF(C168=D168, "Same","New") -> Same | F168: 13.5 OZ | G168: 944.5 | H168: REGULAR COCONUT MILK 1/4 PLT | I168: =[1]Sheet1!I168 -> 49 | J168: =C168 & "_A1C1.webp" -> 2171_A1C1.webp | K168: =Sheet4!E168 -> 528
A169: COCONUT & MILK PRODUCTS | B169: GOYA COCONUT MILK | C169: 2182 | D169: 2182 | E169: =IF(C169=D169, "Same","New") -> Same | F169: 8 OZ | G169: 30.5 | H169: GOYA COCONUT MILK 8 OZ | I169: =[1]Sheet1!I169 -> 90 | J169: =C169 & "_A1C1.webp" -> 2182_A1C1.webp | K169: =Sheet4!E169 -> 24
A170: BEVERAGES | B170: GOYA COCONUT WATER | C170: 2195 | D170: 2195 | E170: =IF(C170=D170, "Same","New") -> Same | F170: 13.5 OZ | G170: 18.95 | H170: GOYA COCONUT WATER 13.5 OZ | I170: =[1]Sheet1!I170 -> 2509 | J170: =C170 & "_A1C1.webp" -> 2195_A1C1.webp | K170: =Sheet4!E170 -> 12
A171: COOKING BASES AND SAUCES | B171: GOYA KETCHUP - MAYONNAISE - CHIMICHURRI | C171: 2197 | D171: 2197 | E171: =IF(C171=D171, "Same","New") -> Same | F171: =Sheet4!F171 -> 7 OZ | H171: =Sheet4!H171 -> SALSITA TOMATO SAUCE W CHEESE | I171: =[1]Sheet1!I171 -> 0 | J171: =C171 & "_A1C1.webp" -> 2197_A1C1.webp | K171: =Sheet4!E171 -> 24 | L171: New
A172: COOKING BASES AND SAUCES | B172: GOYA KETCHUP - MAYONNAISE - CHIMICHURRI | C172: 2198 | D172: 2198 | E172: =IF(C172=D172, "Same","New") -> Same | F172: =Sheet4!F172 -> 7 OZ | H172: =Sheet4!H172 -> SALSITA CENTROAMERICA RANCHERA | I172: =[1]Sheet1!I172 -> 0 | J172: =C172 & "_A1C1.webp" -> 2198_A1C1.webp | K172: =Sheet4!E172 -> 24 | L172: New
A173: COOKING BASES AND SAUCES | B173: GOYA KETCHUP - MAYONNAISE - CHIMICHURRI | C173: 2199 | D173: 2199 | E173: =IF(C173=D173, "Same","New") -> Same | F173: =Sheet4!F173 -> 7 OZ | H173: =Sheet4!H173 -> SALSITA SOFRITO CRIOLLO 7 OZ | I173: =[1]Sheet1!I173 -> 79 | J173: =C173 & "_A1C1.webp" -> 2199_A1C1.webp | K173: =Sheet4!E173 -> 24 | L173: New
A174: VEGETABLES | B174: GOYA CAN/ ORGANIC VEGETABLES | C174: 2200 | D174: 2200 | E174: =IF(C174=D174, "Same","New") -> Same | F174: 15 OZ | G174: 26.95 | H174: ORGANIC WHOLE KERNEL GLDN CORN | I174: =[1]Sheet1!I174 -> 1516 | J174: =C174 & "_A1C1.webp" -> 2200_A1C1.webp | K174: =Sheet4!E174 -> 12
A175: VEGETABLES | B175: GOYA CAN/ ORGANIC VEGETABLES | C175: 2201 | D175: 2201 | E175: =IF(C175=D175, "Same","New") -> Same | F175: 15 OZ | G175: 26.95 | H175: ORGANIC TENDER SWEET PEAS | I175: =[1]Sheet1!I175 -> 229 | J175: =C175 & "_A1C1.webp" -> 2201_A1C1.webp | K175: =Sheet4!E175 -> 12
A176: VEGETABLES | B176: GOYA CAN/ ORGANIC VEGETABLES | C176: 2203 | D176: 2203 | E176: =IF(C176=D176, "Same","New") -> Same | F176: 14.5 OZ | G176: 26.95 | H176: ORGANIC CUT GREEN BEANS | I176: =[1]Sheet1!I176 -> 549 | J176: =C176 & "_A1C1.webp" -> 2203_A1C1.webp | K176: =Sheet4!E176 -> 12
A177: VEGETABLES | B177: GOYA CAN/ ORGANIC VEGETABLES | C177: 2204 | D177: 2204 | E177: =IF(C177=D177, "Same","New") -> Same | F177: 15 OZ | G177: 32.95 | H177: ORGANIC PUMPKIN PUREE | I177: =[1]Sheet1!I177 -> 349 | J177: =C177 & "_A1C1.webp" -> 2204_A1C1.webp | K177: =Sheet4!E177 -> 12
A178: VEGETABLES | B178: GOYA CAN/ VEGETABLES | C178: 2272 | D178: 2272 | E178: =IF(C178=D178, "Same","New") -> Same | F178: 106 OZ | G178: 41.95 | H178: GOYA WHOLE KERNEL GOLDEN CORN | I178: =[1]Sheet1!I178 -> 570 | J178: =C178 & "_A1C1.webp" -> 2272_A1C1.webp | K178: =Sheet4!E178 -> 6
A179: VEGETABLES | B179: GOYA CAN/ VEGETABLES | C179: 2273 | D179: 2273 | E179: =IF(C179=D179, "Same","New") -> Same | F179: 29 OZ | G179: 26.95 | H179: GOYA WHOLE KERNEL GOLDEN CORN | I179: =[1]Sheet1!I179 -> 371 | J179: =C179 & "_A1C1.webp" -> 2273_A1C1.webp | K179: =Sheet4!E179 -> 12
A180: BEANS, LENTILS, PEAS & BAGGED GRAINS | B180: GOYA DRY BEANS & LENTILS 50 LB. | C180: 2284 | D180: 2284 | E180: =IF(C180=D180, "Same","New") -> Same | F180: 801 OZ | G180: 60.95 | H180: CHICK PEAS 50 LBS | I180: =[1]Sheet1!I180 -> 0 | J180: =C180 & "_A1C1.webp" -> 2284_A1C1.webp | K180: =Sheet4!E180 -> 1
A181: BEANS, LENTILS, PEAS & BAGGED GRAINS | B181: GOYA LOW SODIUM BEANS & PEAS 15 OZ. / 15.5 OZ. | C181: 2286 | D181: 2286 | E181: =IF(C181=D181, "Same","New") -> Same | F181: 15.5 OZ | G181: 26.4 | H181: LOW-SODIUM ROMAN BEANS | I181: =[1]Sheet1!I181 -> 368 | J181: =C181 & "_A1C1.webp" -> 2286_A1C1.webp | K181: =Sheet4!E181 -> 24
A182: BEANS, LENTILS, PEAS & BAGGED GRAINS | B182: GOYA LOW SODIUM BEANS & PEAS 15 OZ. / 15.5 OZ. | C182: 2287 | D182: 2287 | E182: =IF(C182=D182, "Same","New") -> Same | F182: 15.5 OZ | G182: 26.4 | H182: LOW-SODIUM SMALL RED BEANS | I182: =[1]Sheet1!I182 -> 2236 | J182: =C182 & "_A1C1.webp" -> 2287_A1C1.webp | K182: =Sheet4!E182 -> 24
A183: BEANS, LENTILS, PEAS & BAGGED GRAINS | B183: GOYA BEANS, LENTILS, PEAS & DRY GRAINS 16 OZ. | C183: 2288 | D183: 2288 | E183: =IF(C183=D183, "Same","New") -> Same | F183: 16 OZ | G183: 55.95 | H183: FRENCH LENTILS 16 OZ | I183: =[1]Sheet1!I183 -> 131 | J183: =C183 & "_A1C1.webp" -> 2288_A1C1.webp | K183: =Sheet4!E183 -> 24
A184: BEANS, LENTILS, PEAS & BAGGED GRAINS | B184: GOYA PREMIUM BEANS & PEAS 15 OZ./15.5 OZ. - QTR PALLET | C184: 2289 | D184: 2289 | E184: =IF(C184=D184, "Same","New") -> Same | F184: 15.5 OZ | G184: 580.8 | H184: BLACK-PINK BL 1/4 PLT 15.5 OZ | I184: =[1]Sheet1!I184 -> 64 | J184: =C184 & "_A1C1.webp" -> 2289_A1C1.webp | K184: =Sheet4!E184 -> 528
...

Sheet Sheet4
A1: LAWSON COMPANY | B1: LAWSON LOCATION | C1: COMPANY | D1: PRODUCT NUMBER | E1: PACK SIZE | F1: PRODUCT SIZE | G1: PRODUCT PACKED TYPE | H1: PRODUCT DESCRIPTION | I1: QUANTITY ON HAND | J1: QUANTITY ON ORDER | K1: 8 WEEK DEMAND CYCLE | L1: AVG. DEMD | M1: WEEKLY SUPPLY | N1: AVAILABLE WEEKS SUPPLY
A2: 1 | B2: 100 | C2: 01 | D2: 1103 | E2: 36 | F2: 3 OZ | G2: BOT | H2: EXTRA VIRGIN OLIVE OIL 3 OZ | I2: 1067 | J2: 1260 | L2: 108.85 | M2: 21.4 | N2: 9.8
A3: 1 | B3: 100 | C3: 01 | D3: 1105 | E3: 25 | F3: 8.5 OZ | G3: BOT | H3: EXTRA VIRGIN OLIVE OIL 8.5 OZ | I3: 2799 | J3: 2808 | L3: 282.28 | M3: 19.9 | N3: 9.9
A4: 1 | B4: 100 | C4: 01 | D4: 1107 | E4: 12 | F4: 17 OZ | G4: BOT | H4: EXTRA VIRGIN OLIVE OIL 17 OZ | I4: 4070 | J4: 3610 | L4: 506.14 | M4: 15.2 | N4: 8
A5: 1 | B5: 100 | C5: 01 | D5: 1108 | E5: 9 | F5: 25.4 OZ | G5: BOT | H5: EXTRA VIRGIN OLIVE OIL 25.4 OZ | I5: 302 | J5: 180 | L5: 17.14 | M5: 28.1 | N5: 17.6
A6: 1 | B6: 100 | C6: 01 | D6: 1109 | E6: 9 | F6: 34 OZ | G6: BOT | H6: EXTRA VIRGIN OLIVE OIL 34 OZ | I6: 1453 | J6: 800 | L6: 112.71 | M6: 20 | N6: 12.9
A7: 1 | B7: 100 | C7: 01 | D7: 1111 | E7: 6 | F7: 50.7 OZ | G7: BOT | H7: EXTRA VIRGIN OLIVE OIL 50.7 OZ | I7: 134 | J7: 0 | L7: 7.42 | M7: 18.1 | N7: 18.1
A8: 1 | B8: 100 | C8: 01 | D8: 1120 | E8: 12 | F8: 24 OZ | G8: CAN | H8: EXTRA VIRGIN OLIVE OIL 24 OZ | I8: 3 | J8: 14 | L8: 0.57 | M8: 29.8 | N8: 5.3
A9: 1 | B9: 100 | C9: 01 | D9: 1128 | E9: 3 | F9: 101 OZ | G9: CAN | H9: EXTRA VIRGIN OLIVE OIL 3 LTS | I9: 78 | J9: 0 | L9: 3.57 | M9: 21.8 | N9: 21.8
A10: 1 | B10: 100 | C10: 01 | D10: 1130 | E10: 12 | F10: 17 OZ | G10: BOT | H10: GOYA UNICO XTRA VIRGIN OLV OIL | I10: 72 | J10: 95 | L10: 6.14 | M10: 27.2 | N10: 11.7
A11: 1 | B11: 100 | C11: 01 | D11: 1133 | E11: 12 | F11: 17 OZ | G11: BOT | H11: ORGANIC EXTRA VIRGIN OLIVE OIL | I11: 32 | J11: 285 | L11: 18 | M11: 17.6 | N11: 1.8
A12: 1 | B12: 100 | C12: 01 | D12: 1141 | E12: 25 | F12: 8.5 OZ | G12: BOT | H12: PURO OLIVE OIL 8.5 OZ | I12: 191 | J12: 1014 | L12: 66.71 | M12: 18.1 | N12: 2.9
A13: 1 | B13: 100 | C13: 01 | D13: 1142 | E13: 12 | F13: 17 OZ | G13: BOT | H13: PURO OLIVE OIL 17 OZ | I13: 352 | J13: 570 | L13: 45.14 | M13: 20.4 | N13: 7.8
... A24: 1 | B24: 100 | C24: 01 | D24: 1195 | E24: 12 | F24: 8.5 OZ | G24: BOT | H24: GARLIC EXTRA VIRGIN OLIVE OIL | I24: 90 | J24: 336 | L24: 21.57 | M24: 19.7 | N24: 4.2
A25: 1 | B25: 100 | C25: 01 | D25: 1199 | E25: 12 | F25: 5 OZ | H25: EXTRA VIRGIN OLIVE OIL SPRAY | I25: 555 | J25: 0 | L25: 25.14 | M25: 22.1 | N25: 22.1
A26: 1 | B26: 100 | C26: 01 | D26: 1222 | E26: 2 | F26: 280 OZ | G26: BOT | H26: PURE CORN OIL 280 OZ | I26: 157 | J26: 80 | L26: 6.28 | M26: 37.7 | N26: 25
A27: 1 | B27: 100 | C27: 01 | D27: 1227 | E27: 24 | F27: 16 OZ | G27: BOT | H27: PURE CORN OIL 16 OZ | I27: 486 | J27: 1280 | L27: 122.42 | M27: 14.4 | N27: 4
A28: 1 | B28: 100 | C28: 01 | D28: 1229 | E28: 12 | F28: 24 OZ | G28: BOT | H28: PURE CORN OIL 24 OZ | I28: 873 | J28: 1326 | L28: 191.42 | M28: 11.5 | N28: 4.6
A29: 1 | B29: 100 | C29: 01 | D29: 1231 | E29: 9 | F29: 48 OZ | G29: BOT | H29: PURE CORN OIL 48 OZ | I29: 482 | J29: 1560 | L29: 171.71 | M29: 11.9 | N29: 2.8
A30: 1 | B30: 100 | C30: 01 | D30: 1233 | E30: 6 | F30: 128 OZ | G30: BOT | H30: PURE CORN OIL 1 GAL | I30: 98 | J30: 252 | L30: 33 | M30: 10.6 | N30: 3
A31: 1 | B31: 100 | C31: 01 | D31: 1234 | E31: 6 | F31: 96 OZ | G31: BOT | H31: PURE CORN OIL 96 OZ | I31: 417 | J31: 72 | L31: 28 | M31: 17.5 | N31: 14.9
A32: 1 | B32: 100 | C32: 01 | D32: 1235 | E32: 24 | F32: 16 OZ | G32: BOT | H32: VEGETABLE OIL 16 OZ | I32: 642 | J32: 1080 | L32: 179.14 | M32: 9.6 | N32: 3.6
A33: 1 | B33: 100 | C33: 01 | D33: 1237 | E33: 12 | F33: 24 OZ | G33: BOT | H33: VEGETABLE OIL 24 OZ | I33: 1129 | J33: 2328 | L33: 301.57 | M33: 11.5 | N33: 3.7
A34: 1 | B34: 100 | C34: 01 | D34: 1239 | E34: 9 | F34: 48 OZ | G34: BOT | H34: VEGETABLE OIL 48 OZ | I34: 603 | J34: 2520 | L34: 276.57 | M34: 11.3 | N34: 2.2
A35: 1 | B35: 100 | C35: 01 | D35: 1240 | E35: 6 | F35: 96 OZ | G35: BOT | H35: VEGETABLE OIL 96 OZ | I35: 130 | J35: 396 | L35: 32.71 | M35: 16.1 | N35: 4
A36: 1 | B36: 100 | C36: 01 | D36: 1241 | E36: 6 | F36: 128 OZ | G36: BOT | H36: VEGETABLE OIL 1 GAL | I36: 308 | J36: 216 | L36: 28.71 | M36: 18.3 | N36: 10.7
A37: 1 | B37: 100 | C37: 01 | D37: 1250 | E37: 9 | F37: 48 OZ | G37: BOT | H37: CANOLA OIL 48 OZ | I37: 25 | J37: 1140 | L37: 99.28 | M37: 13.5 | N37: 0.3
A38: 1 | B38: 100 | C38: 01 | D38: 1251 | E38: 6 | F38: 96 OZ | H38: CANOLA OIL 96 OZ | I38: 166 | J38: 224 | L38: 6.85 | M38: 56.9 | N38: 24.2
A39: 1 | B39: 100 | C39: 01 | D39: 1255 | E39: 6 | F39: 25.4 OZ | G39: BOT | H39: GOYA AVOCADO OIL 25.4 OZ | I39: 1653 | J39: 2700 | L39: 138.28 | M39: 31.5 | N39: 12
A40: 1 | B40: 100 | C40: 01 | D40: 1304 | E40: 12 | F40: 9.5 OZ | G40: JAR | H40: PERDIGON OLIVES 12/9.5 OZ | I40: 72 | J40: 648 | L40: 17.42 | M40: 41.3 | N40: 4.1
A41: 1 | B41: 100 | C41: 01 | D41: 1307 | E41: 12 | F41: 3.75 OZ | G41: JAR | H41: MANZANILLA OLIVES | I41: 184 | J41: 192 | L41: 11.85 | M41: 31.7 | N41: 15.5
A42: 1 | B42: 100 | C42: 01 | D42: 1309 | E42: 12 | F42: 9.5 OZ | G42: JAR | H42: MANZANILLA OLIVES 9.5 OZ | I42: 675 | J42: 432 | L42: 48.71 | M42: 22.7 | N42: 13.9
A43: 1 | B43: 100 | C43: 01 | D43: 1312 | E43: 12 | F43: 20 OZ | G43: JAR | H43: PERDIGON OLIVES 20 OZ | I43: 205 | J43: 240 | L43: 11.71 | M43: 38 | N43: 17.5
A44: 1 | B44: 100 | C44: 01 | D44: 1317 | E44: 12 | F44: 2.25 OZ | G44: JAR | H44: COCKTAIL PITTED OLIVES | I44: 191 | J44: 560 | L44: 24.14 | M44: 31.1 | N44: 7.9
A45: 1 | B45: 100 | C45: 01 | D45: 1319 | E45: 24 | F45: 5.5 OZ | G45: JAR | H45: COCKTAIL PITTED OLIVES 5.5 OZ | I45: 1909 | J45: 2940 | L45: 241.42 | M45: 20.1 | N45: 7.9
A46: 1 | B46: 100 | C46: 01 | D46: 1327 | E46: 12 | F46: 3.75 OZ | G46: JAR | H46: STUFF MANZANILLA OLIVES | I46: 727 | J46: 768 | L46: 61.14 | M46: 24.5 | N46: 11.9
A47: 1 | B47: 100 | C47: 01 | D47: 1331 | E47: 12 | F47: 9.5 OZ | G47: JAR | H47: STUFF MANZANILLA OLIVES 9.5 OZ | I47: 2272 | J47: 3888 | L47: 274 | M47: 22.5 | N47: 8.3
A48: 1 | B48: 100 | C48: 01 | D48: 1332 | E48: 12 | F48: 20 OZ | G48: JAR | H48: STUFF MANZANILLA OLIVES 20 OZ | I48: 446 | J48: 600 | L48: 39.28 | M48: 26.6 | N48: 11.4
A49: 1 | B49: 100 | C49: 01 | D49: 1333 | E49: 12 | F49: 3.375 OZ | G49: JAR | H49: STUFFED QUEEN OLIVES | I49: 113 | J49: 192 | L49: 13.85 | M49: 22 | N49: 8.2
A50: 1 | B50: 100 | C50: 01 | D50: 1335 | E50: 12 | F50: 9 OZ | G50: JAR | H50: STUFFED QUEEN OLIVES 9 OZ | I50: 261 | J50: 324 | L50: 28.57 | M50: 20.5 | N50: 9.1
... A179: 1 | B179: 100 | C179: 01 | D179: 2273 | E179: 12 | F179: 29 OZ | G179: CAN | H179: GOYA WHOLE KERNEL GOLDEN CORN | I179: 385 | J179: 200 | L179: 41.28 | M179: 14.2 | N179: 9.3
A180: 1 | B180: 100 | C180: 01 | D180: 2284 | E180: 1 | F180: 801 OZ | H180: CHICK PEAS 50 LBS | I180: 0 | J180: 0 | L180: 0.28 | M180: 0 | N180: 0
A181: 1 | B181: 100 | C181: 01 | D181: 2286 | E181: 24 | F181: 15.5 OZ | G181: CAN | H181: LOW-SODIUM ROMAN BEANS | I181: 381 | J181: 480 | L181: 51.57 | M181: 16.7 | N181: 7.4
A182: 1 | B182: 100 | C182: 01 | D182: 2287 | E182: 24 | F182: 15.5 OZ | G182: CAN | H182: LOW-SODIUM SMALL RED BEANS | I182: 2283 | J182: 0 | L182: 173.57 | M182: 13.2 | N182: 13.2
A183: 1 | B183: 100 | C183: 01 | D183: 2288 | E183: 24 | F183: 16 OZ | G183: BAG | H183: FRENCH LENTILS 16 OZ | I183: 132 | J183: 0 | L183: 7 | M183: 18.9 | N183: 18.9
A184: 1 | B184: 100 | C184: 01 | D184: 2289 | E184: 528 | F184: 15.5 OZ | G184: CAN | H184: BLACK-PINK BL 1/4 PLT 15.5 OZ | I184: 64 | J184: 0 | L184: 0 | M184: 0 | N184: 9999
A185: 1 | B185: 100 | C185: 01 | D185: 2330 | E185: 24 | F185: 15.5 OZ | G185: CAN | H185: RED KIDNEY LOW SODIUM 15.5 OZ | I185: 4022 | J185: 1760 | L185: 399.71 | M185: 14.5 | N185: 10.1
A186: 1 | B186: 100 | C186: 01 | D186: 2331 | E186: 24 | F186: 15.5 OZ | G186: CAN | H186: PINK BEANS LOW SODIUM 15.5 OZ | I186: 4682 | J186: 0 | L186: 315.57 | M186: 14.8 | N186: 14.8
A187: 1 | B187: 100 | C187: 01 | D187: 2332 | E187: 24 | F187: 15.5 OZ | G187: CAN | H187: BLACK BEANS LOW SODIUM 15.5 OZ | I187: 8516 | J187: 12320 | L187: 1155.85 | M187: 18 | N187: 7.4
A188: 1 | B188: 100 | C188: 01 | D188: 2333 | E188: 24 | F188: 15.5 OZ | G188: CAN | H188: CHICK PEAS LOW SODIUM 15.5 OZ | I188: 3340 | J188: 4560 | L188: 759 | M188: 10.4 | N188: 4.4
A189: 1 | B189: 100 | C189: 01 | D189: 2334 | E189: 24 | F189: 15.5 OZ | G189: CAN | H189: PINTO BEANS LOW SODIUM 15.5 OZ | I189: 2032 | J189: 720 | L189: 177.14 | M189: 15.5 | N189: 11.5
A190: 1 | B190: 100 | C190: 01 | D190: 2335 | E190: 24 | F190: 15.5 OZ | G190: CAN | H190: SMALL WHT BNS LOW SODIUM 15.5 | I190: 1666 | J190: 800 | L190: 121.71 | M190: 20.3 | N190: 13.7
A191: 1 | B191: 100 | C191: 01 | D191: 2340 | E191: 24 | F191: 15.5 OZ | G191: CAN | H191: ORGANIC RED KIDNEY 24/15.5 OZ | I191: 3541 | J191: 0 | L191: 283.57 | M191: 12.5 | N191: 12.5
A192: 1 | B192: 100 | C192: 01 | D192: 2341 | E192: 24 | F192: 15.5 OZ | G192: CAN | H192: ORGANIC PINTO BEANS | I192: 1130 | J192: 0 | L192: 73.28 | M192: 15.4 | N192: 15.4
... A722: 1 | B722: 100 | C722: 01 | D722: 3181 | E722: 36 | F722: 3.5 OZ | G722: BOX | H722: CORN MAJARETE PUDDING 3 1/2 OZ | I722: 64 | J722: 216 | L722: 15.42 | M722: 18.2 | N722: 4.2
A723: 1 | B723: 100 | C723: 01 | D723: 3182 | E723: 24 | F723: 8 OZ | H723: LIME JUICE 8 FL.OZ | I723: 62 | J723: 0 | L723: 4 | M723: 15.5 | N723: 15.5
A724: 1 | B724: 100 | C724: 01 | D724: 3183 | E724: 36 | F724: 3.5 OZ | G724: BOX | H724: TEMBLEQUE 3 1/2 OZ | I724: 292 | J724: 0 | L724: 19.42 | M724: 15 | N724: 15
A725: 1 | B725: 100 | C725: 01 | D725: 3184 | E725: 36 | F725: 3.25 OZ | G725: BOX | H725: NATILLA 3.25 OZ | I725: 51 | J725: 0 | L725: 4.28 | M725: 11.9 | N725: 11.9
A726: 1 | B726: 100 | C726: 01 | D726: 3185 | E726: 36 | F726: 2 OZ | G726: BOX | H726: FLAN 2 OZ | I726: 44 | J726: 72 | L726: 7.71 | M726: 15 | N726: 5.7
A727: 1 | B727: 100 | C727: 01 | D727: 3186 | E727: 36 | F727: 4 OZ | G727: BOX | H727: FLAN 4 OZ | I727: 101 | J727: 0 | L727: 7.71 | M727: 13.1 | N727: 13.1
A728: 1 | B728: 100 | C728: 01 | D728: 3187 | E728: 36 | F728: 2.75 OZ | G728: BOX | H728: FLAN WITH CARAMEL 2 3/4 OZ | I728: 98 | J728: 0 | L728: 9.42 | M728: 10.4 | N728: 10.4
A729: 1 | B729: 100 | C729: 01 | D729: 3188 | E729: 36 | F729: 5.5 OZ | G729: BOX | H729: FLAN WITH CARAMEL 5 1/2 OZ | I729: 378 | J729: 324 | L729: 42.14 | M729: 16.7 | N729: 9
A730: 1 | B730: 100 | C730: 01 | D730: 3190 | E730: 20 | F730: 14.1 OZ | G730: BOX | H730: GOYA PAN DE BONO 20/14.1 OZ | I730: 2 | J730: 0 | L730: 1 | M730: 2 | N730: 2
A731: 1 | B731: 100 | C731: 01 | D731: 3191 | E731: 20 | F731: 14.11 OZ | G731: BOX | H731: GOYA BUNUELOS 20/14.11 OZ | I731: 0 | J731: 0 | L731: 0 | M731: 0 | N731: 9999
A732: 1 | B732: 100 | C732: 01 | D732: 3192 | E732: 20 | F732: 14.1 OZ | G732: BOX | H732: GOYA NATILLA 20/14.1 OZ | I732: 0 | J732: 0 | L732: 0.57 | M732: 0 | N732: 0
A733: 1 | B733: 100 | C733: 01 | D733: 3200 | E733: 24 | F733: 16 OZ | G733: JAR | H733: PLAIN HONEY 16 OZ | I733: 205 | J733: 750 | L733: 21.42 | M733: 44.6 | N733: 9.6
A734: 1 | B734: 100 | C734: 01 | D734: 3201 | E734: 24 | F734: 8 OZ | G734: JAR | H734: ELOTITOS TIERNOS 8 OZ. | I734: 369 | J734: 0 | L734: 2.42 | M734: 152.5 | N734: 152.5
A735: 1 | B735: 100 | C735: 01 | D735: 3202 | E735: 24 | F735: 8 OZ | G735: BOT | H735: PLAIN HONEY 8 OZ | I735: 506 | J735: 448 | L735: 47.14 | M735: 20.2 | N735: 10.7
... A813: 1 | B813: 100 | C813: 01 | D813: 3590 | E813: 6 | F813: 19 OZ | G813: BOX | H813: GOYA VEGAN PAELLA 19 OZ | I813: 74 | J813: 0 | L813: 2 | M813: 37 | N813: 37
A814: 1 | B814: 100 | C814: 01 | D814: 3596 | E814: 18 | F814: 1.41 OZ | H814: SAZON GOYA AZAFRAN 18PK 1.41OZ | I814: 0 | J814: 0 | L814: 0 | M814: 0 | N814: 9999
A815: 1 | B815: 100 | C815: 01 | D815: 3599 | E815: 6 | F815: 19 OZ | G815: BOX | H815: GOYA BLK SQUID INK PAELLA KIT | I815: 128 | J815: 0 | L815: 6 | M815: 21.3 | N815: 21.3
A816: 1 | B816: 100 | C816: 01 | D816: 3600 | E816: 12 | F816: 15.9 OZ | G816: BOT | H816: CONDENSED MILK SQUEEZE BOTTLE | I816: 334 | J816: 0 | L816: 8 | M816: 41.8 | N816: 41.8
A817: 1 | B817: 100 | C817: 01 | D817: 3602 | E817: 12 | F817: 4.25 OZ | G817: CAN | H817: SARDINES SUNFLOWER OIL | I817: 17 | J817: 168 | L817: 8.71 | M817: 21.2 | N817: 2
A818: 1 | B818: 100 | C818: 01 | D818: 3607 | E818: 25 | F818: 4 OZ | G818: CAN | H818: JUMBO SQUID IN VEGETABLE OIL | I818: 68 | J818: 26 | L818: 5.14 | M818: 18.3 | N818: 13.2
A819: 1 | B819: 100 | C819: 01 | D819: 3609 | E819: 25 | F819: 4.25 OZ | G819: CAN | H819: SARDINES LEMON 4 1/4 OZ | I819: 357 | J819: 572 | L819: 12.14 | M819: 76.5 | N819: 29.4
A820: 1 | B820: 100 | C820: 01 | D820: 3610 | E820: 25 | F820: 4.25 OZ | G820: CAN | H820: SARDINES OLIVE OIL 4 1/4 OZ | I820: 2075 | J820: 2834 | L820: 94.42 | M820: 52 | N820: 22
A821: 1 | B821: 100 | C821: 01 | D821: 3611 | E821: 25 | F821: 4.25 OZ | G821: CAN | H821: SARDINES SPICE 4 1/4 OZ | I821: 477 | J821: 598 | L821: 13.71 | M821: 78.4 | N821: 34.8
A822: 1 | B822: 100 | C822: 01 | D822: 3612 | E822: 25 | F822: 4.25 OZ | G822: CAN | H822: SARDINES TMTO SAUCE 4 1/4 OZ | I822: 528 | J822: 676 | L822: 23.85 | M822: 50.5 | N822: 22.1
A823: 1 | B823: 100 | C823: 01 | D823: 3613 | E823: 24 | F823: 15 OZ | G823: CAN | H823: OVAL SARDINE TMTO SAUCE 15 OZ | I823: 679 | J823: 5750 | L823: 302.42 | M823: 21.3 | N823: 2.2
A824: 1 | B824: 100 | C824: 01 | D824: 3615 | E824: 50 | F824: 5.5 OZ | G824: CAN | H824: SARDINE TMTO SCE-TINAPA 5.5 OZ | I824: 958 | J824: 600 | L824: 61.28 | M824: 25.4 | N824: 15.6
A825: 1 | B825: 100 | C825: 01 | D825: 3616 | E825: 24 | F825: 15 OZ | G825: CAN | H825: OVAL SARDINE HOT SAUCE 15 OZ | I825: 800 | J825: 1700 | L825: 134.14 | M825: 18.6 | N825: 6
A826: 1 | B826: 100 | C826: 01 | D826: 3617 | E826: 50 | F826: 5.5 OZ | G826: CAN | H826: SARDINE TMTO HOT-TINAPA 5.5 OZ | I826: 1871 | J826: 1300 | L826: 130.42 | M826: 24.3 | N826: 14.3
... A863: 1 | B863: 100 | C863: 01 | D863: 3691 | E863: 24 | F863: 12 OZ | G863: CAN | H863: GOYA EVAPORATED MILK | I863: 2303 | J863: 1836 | L863: 86 | M863: 48.1 | N863: 26.8
A864: 1 | B864: 100 | C864: 01 | D864: 3694 | E864: 456 | G864: DIS | H864: COQUITO QUARTER PALLET | I864: 0 | J864: 0 | L864: 0 | M864: 0 | N864: 9999
A865: 1 | B865: 100 | C865: 01 | D865: 3695 | E865: 24 | F865: 14 OZ | G865: CAN | H865: NELA SWTENED CONDENS FILL MILK | I865: 69 | J865: 0 | L865: 10.28 | M865: 6.7 | N865: 6.7
A866: 1 | B866: 100 | C866: 01 | D866: 3696 | E866: 24 | F866: 12 OZ | G866: CAN | H866: NELA EVAPORATED FILLED MILK 12 | I866: 775 | J866: 0 | L866: 20.71 | M866: 37.4 | N866: 37.4
A867: 1 | B867: 100 | C867: 01 | D867: 3706 | E867: 24 | F867: 9 OZ | G867: JAR | H867: GOYA ADOBO W/MDTRRNN SEA SALT | I867: 28 | J867: 0 | L867: 2.71 | M867: 10.3 | N867: 10.3
A868: 1 | B868: 100 | C868: 01 | D868: 3713 | E868: 12 | F868: 15 OZ | G868: CAN | H868: GOYA NACHO CHEESE SAUCE MILD | I868: 605 | J868: 0 | L868: 1.28 | M868: 472.7 | N868: 472.7
A869: 1 | B869: 100 | C869: 01 | D869: 3714 | E869: 12 | F869: 15 OZ | G869: CAN | H869: GOYA NACHO CHEESE SAUCE ZESTY | I869: 275 | J869: 0 | L869: 0.71 | M869: 387.3 | N869: 387.3
A870: 1 | B870: 100 | C870: 01 | D870: 3718 | E870: 12 | F870: 18 OZ | G870: JAR | H870: SAZONADOR TOTAL WITH PEPPER | I870: 234 | J870: 0 | L870: 15 | M870: 15.6 | N870: 15.6
A871: 1 | B871: 100 | C871: 01 | D871: 3720 | E871: 24 | F871: 5 Oz | G871: CAN | H871: GOYA CHILIN 5 OZ | I871: 0 | J871: 0 | L871: 0 | M871: 0 | N871: 9999
A872: 1 | B872: 100 | C872: 01 | D872: 3721 | E872: 12 | F872: 5 OZ | G872: POU | H872: CORTES MOLIDO POUCH LITE 5 OZ | I872: 0 | J872: 300 | L872: 1.57 | M872: 191.1 | N872: 0
A873: 1 | B873: 100 | C873: 01 | D873: 3724 | E873: 12 | F873: 0.2 OZ | G873: JAR | H873: TILO/LINDEN FLOWER .2 OZ | I873: 13 | J873: 0 | L873: 0.42 | M873: 31 | N873: 31
A874: 1 | B874: 100 | C874: 01 | D874: 3726 | E874: 12 | F874: 1.25 OZ | G874: JAR | H874: GROUND OREGANO 1.25OZ | I874: 68 | J874: 0 | L874: 3.71 | M874: 18.3 | N874: 18.3
A875: 1 | B875: 100 | C875: 01 | D875: 3727 | E875: 12 | F875: 1.5 OZ | G875: JAR | H875: ALL SPICE 1.5 OZ | I875: 143 | J875: 0 | L875: 1.85 | M875: 77.3 | N875: 77.3
A876: 1 | B876: 100 | C876: 01 | D876: 3728 | E876: 12 | F876: 1.8 OZ | G876: JAR | H876: ANIS SEED 1.8 OZ | I876: 14 | J876: 0 | L876: 2.28 | M876: 6.1 | N876: 6.1
... A1439: 1 | B1439: 100 | C1439: 01 | D1439: 5998 | E1439: 12 | F1439: 8.8 OZ | G1439: POU | H1439: GOYA BROWN RICE POUCH | I1439: 0 | J1439: 0 | L1439: 0 | M1439: 0 | N1439: 9999
A1440: 1 | B1440: 100 | C1440: 01 | D1440: 6037 | E1440: 1 | F1440: 120 OZ | H1440: GOYA GANDULES 8 PACK 15 OZ | I1440: 166914 | J1440: 10560 | L1440: 3429 | M1440: 51.8 | N1440: 48.7
A1441: 1 | B1441: 100 | C1441: 01 | D1441: 6038 | E1441: 1 | F1441: 124 OZ | G1441: CAN | H1441: GOYA BLACK BEANS 8/15.5 OZ. | I1441: 14995 | J1441: 15600 | L1441: 901.71 | M1441: 33.9 | N1441: 16.6
A1442: 1 | B1442: 100 | C1442: 01 | D1442: 6039 | E1442: 1 | F1442: 124 OZ | G1442: CAN | H1442: GOYA PINTO BEANS 8/15.5 OZ. | I1442: 240 | J1442: 0 | L1442: 171.42 | M1442: 1.4 | N1442: 1.4
...

Sheet Sheet5

Sheet Sheet2
A1: # | B1: CATEGORIA | C1: SUBCATEGORIA | D1: ITEM # | E1: DESCRIPCION | F1: CASE COST | G1: UNIT COST | H1: UNIT PRICE | I1: SUGGEST RETAIL
A2: 1220 | B2: OLIVE OIL - OILS & LARD | C2: GOYA EXTRA VIRGIN OLIVE OIL | D2: 1103 | E2: 36/3 oz | F2: 77.50 | G2: 2.15 | H2: 15.41 | I2: 2.89
A3: 1221 | B3: OLIVE OIL - OILS & LARD | C3: GOYA EXTRA VIRGIN OLIVE OIL | D3: 1105 | E3: 25/8.5 oz | F3: 131.95 | G3: 5.28 | H3: 13.16 | I3: 6.99
A4: 1222 | B4: OLIVE OIL - OILS & LARD | C4: GOYA EXTRA VIRGIN OLIVE OIL | D4: 1107 | E4: 12/17 oz | F4: 120.50 | G4: 10.04 | H4: 12.60 | I4: 13.39
A5: 1223 | B5: OLIVE OIL - OILS & LARD | C5: GOYA EXTRA VIRGIN OLIVE OIL | D5: 1108 | E5: 9/25.4 oz | F5: 134.95 | G5: 14.99 | H5: 12.59 | I5: 19.99
A6: 1224 | B6: OLIVE OIL - OILS & LARD | C6: GOYA EXTRA VIRGIN OLIVE OIL | D6: 1109 | E6: 9/34 oz | F6: 169.95 | G6: 18.88 | H6: 11.85 | I6: 25.19
A7: 1225 | B7: OLIVE OIL - OILS & LARD | C7: GOYA EXTRA VIRGIN OLIVE OIL | D7: 1111 | E7: 6/50.7 oz | F7: 168.95 | G7: 28.16 | H7: 11.83 | I7: 37.49
A8: 1226 | B8: OLIVE OIL - OILS & LARD | C8: GOYA EXTRA VIRGIN OLIVE OIL | D8: 1120 | E8: 12/24 oz tin | F8: 171.95 | G8: 14.33 | H8: 12.66 | I8: 18.99
A9: 1227 | B9: OLIVE OIL - OILS & LARD | C9: GOYA EXTRA VIRGIN OLIVE OIL | D9: 1128 | E9: 3/3 liter (102 oz) tin | F9: 170.50 | G9: 56.83 | H9: 11.89 | I9: 75.79
A10: 1228 | B10: OLIVE OIL - OILS & LARD | C10: GOYA EXTRA VIRGIN OLIVE OIL | D10: 1130 | E10: 12/17 oz unico | F10: 144.95 | G10: 12.08 | H10: 15.05 | I10: 15.99
A11: 1229 | B11: OLIVE OIL - OILS & LARD | C11: GOYA EXTRA VIRGIN OLIVE OIL | D11: 1133 | E11: 12/17 oz organic | F11: 135.35 | G11: 11.28 | H11: 14.11 | I11: 14.99
A12: 1212 | B12: OLIVE OIL - OILS & LARD | C12: GOYA OLIVE OIL | D12: 1141 | E12: 25/8.5 oz puro olive oil | F12: 113.50 | G12: 4.54 | H12: 11.28 | I12: 5.99
A13: 1213 | B13: OLIVE OIL - OILS & LARD | C13: GOYA OLIVE OIL | D13: 1142 | E13: 12/17 oz puro olive oil | F13: 103.95 | G13: 8.66 | H13: 10.81 | I13: 11.49
... A101: 1355 | B101: PEPPERS - CHILES | C101: GOYA JAR/ JALAPENO PEPPERS | D101: 1686 | E101: 12/12 oz sliced jalapeno peppers | F101: 21.50 | G101: 1.79 | H101: 3.19 | I101: 2.39
A102: 102 | B102: BEANS, LENTILS, PEAS & BAGGED GRAINS | C102: BEANS READY TO EAT - GUISADAS 10.5 OZ. | D102: 1980 | E102: 24/ red kidney beans in sauce | F102: 22.95 | G102: 0.96 | H102: 1.97 | I102: 1.29
A103: 103 | B103: BEANS, LENTILS, PEAS & BAGGED GRAINS | C103: BEANS READY TO EAT - GUISADAS 10.5 OZ. | D103: 1981 | E103: 24/ pink beans in Ssauce | F103: 22.95 | G103: 0.96 | H103: 1.97 | I103: 1.29
A104: 104 | B104: BEANS, LENTILS, PEAS & BAGGED GRAINS | C104: BEANS READY TO EAT - GUISADAS 10.5 OZ. | D104: 1982 | E104: 24/ black bean soup | F104: 22.95 | G104: 0.96 | H104: 1.97 | I104: 1.29
A105: 105 | B105: BEANS, LENTILS, PEAS & BAGGED GRAINS | C105: BEANS READY TO EAT - GUISADAS 10.5 OZ. | D105: 1983 | E105: 24/15.5 oz pinto beans in sauce | F105: 22.95 | G105: 0.96 | H105: 1.97 | I105: 1.29
A106: 106 | B106: BEANS, LENTILS, PEAS & BAGGED GRAINS | C106: BEANS READY TO EAT - GUISADAS 10.5 OZ. | D106: 1984 | E106: 24/15.5 oz small reds in sauce | F106: 22.95 | G106: 0.96 | H106: 1.97 | I106: 1.29
A107: 107 | B107: BEANS, LENTILS, PEAS & BAGGED GRAINS | C107: BEANS READY TO EAT - GUISADAS 10.5 OZ. | D107: 1986 | E107: 24/15.5 oz chick peas in sauce | F107: 22.95 | G107: 0.96 | H107: 1.97 | I107: 1.29
A108: 9 | B108: BEANS, LENTILS, PEAS & BAGGED GRAINS | C108: GOYA PREMIUM BEANS, LENTILS & PEAS 15 OZ. / 15.5 OZ. | D108: 2001 | E108: 24/15 oz green pigeon peas | F108: 34.95 | G108: 1.46 | H108: 2.02 | I108: 1.89
A109: 77 | B109: BEANS, LENTILS, PEAS & BAGGED GRAINS | C109: GOYA LOW SODIUM BEANS & PEAS 15 OZ. / 15.5 OZ. | D109: 2002 | E109: 24/15 oz green pigeon peas low sodium | F109: 34.95 | G109: 1.46 | H109: 2.02 | I109: 1.89
A110: 45 | B110: BEANS, LENTILS, PEAS & BAGGED GRAINS | C110: GOYA PREMIUM BEANS & PEAS 29 OZ. / 30 OZ. | D110: 2003 | E110: 12/29 oz green pigeon peas | F110: 33.25 | G110: 2.77 | H110: 2.04 | I110: 3.69
A111: 70 | B111: BEANS, LENTILS, PEAS & BAGGED GRAINS | C111: GOYA PREMIUM BEANS & PEAS 100.7 OZ. / 110 OZ. | D111: 2004 | E111: 6/100.7 oz green pigeon peas | F111: 53.50 | G111: 8.92 | H111: 1.89 | I111: 11.89
A112: 10 | B112: BEANS, LENTILS, PEAS & BAGGED GRAINS | C112: GOYA PREMIUM BEANS, LENTILS & PEAS 15 OZ. / 15.5 OZ. | D112: 2005 | E112: 24/15 oz green pigeon peas with coconut | F112: 49.50 | G112: 2.06 | H112: 2.87 | I112: 2.69
A113: 46 | B113: BEANS, LENTILS, PEAS & BAGGED GRAINS | C113: GOYA PREMIUM BEANS & PEAS 29 OZ. / 30 OZ. | D113: 2006 | E113: 12/30 oz green pigeon peas with coconut milk | F113: 49.50 | G113: 4.13 | H113: 2.93 | I113: 5.49
A114: 39 | B114: BEANS, LENTILS, PEAS & BAGGED GRAINS | C114: GOYA PREMIUM BEANS & PEAS 15 OZ./15.5 OZ. - QTR PALLET | D114: 2007 | E114: 528/15 oz gandules | F114: 768.90 | G114: 1.46 | H114: 2.02 | I114: 1.89
A115: 94 | B115: BEANS, LENTILS, PEAS & BAGGED GRAINS | C115: GOYA ORGANIC BEANS & PEAS 15 OZ. / 15.5 OZ. | D115: 2009 | E115: 12/15 oz organic - green pigeon peas | F115: 20.95 | G115: 1.75 | H115: 2.44 | I115: 2.29
A116: 11 | B116: BEANS, LENTILS, PEAS & BAGGED GRAINS | C116: GOYA PREMIUM BEANS, LENTILS & PEAS 15 OZ. / 15.5 OZ. | D116: 2010 | E116: 24/15 oz pigeon peas with coconut | F116: 39.50 | G116: 1.65 | H116: 2.34 | I116: 2.19
A117: 37 | B117: BEANS, LENTILS, PEAS & BAGGED GRAINS | C117: GOYA PREMIUM BEANS, LENTILS & PEAS 15 OZ. / 15.5 OZ. | D117: 2021 | E117: 24/15.5 oz pigeon peas - EL JIBARITO | F117: 28.95 | G117: 1.21 | H117: 1.64 | I117: 1.59
A118: 61 | B118: BEANS, LENTILS, PEAS & BAGGED GRAINS | C118: GOYA PREMIUM BEANS & PEAS 29 OZ. / 30 OZ. | D118: 2022 | E118: 12/29 oz pigeon peas - El JIBARITO | F118: 27.25 | G118: 2.27 | H118: 1.65 | I118: 2.99
A119: 38 | B119: BEANS, LENTILS, PEAS & BAGGED GRAINS | C119: GOYA PREMIUM BEANS, LENTILS & PEAS 15 OZ. / 15.5 OZ. | D119: 2023 | E119: 24/15.5 oz pigeon peas with coconut - EL JIBARITO | F119: 39.50 | G119: 1.65 | H119: 2.34 | I119: 2.19
... A221: 13 | B221: BEANS, LENTILS, PEAS & BAGGED GRAINS | C221: GOYA PREMIUM BEANS, LENTILS & PEAS 15 OZ. / 15.5 OZ. | D221: 2402 | E221: 24/15.5 oz red kidney | F221: 26.40 | G221: 1.10 | H221: 1.54 | I221: 1.49
A222: 1 | B222: BEANS, LENTILS, PEAS & BAGGED GRAINS | C222: GOYA PREMIUM BEANS & PEAS 10.5 OZ. | D222: 2403 | E222: 24/ red kidney | F222: 22.50 | G222: .94 | H222: 1.9 | I222: 1.25
A223: 14 | B223: BEANS, LENTILS, PEAS & BAGGED GRAINS | C223: GOYA PREMIUM BEANS, LENTILS & PEAS 15 OZ. / 15.5 OZ. | D223: 2406 | E223: 24/15.5 oz pink beans | F223: 26.40 | G223: 1.10 | H223: 1.54 | I223: 1.49
A224: 2 | B224: BEANS, LENTILS, PEAS & BAGGED GRAINS | C224: GOYA PREMIUM BEANS & PEAS 10.5 OZ. | D224: 2407 | E224: 24/ pink beans | F224: 22.50 | G224: .94 | H224: 1.9 | I224: 1.25
A225: 49 | B225: BEANS, LENTILS, PEAS & BAGGED GRAINS | C225: GOYA PREMIUM BEANS & PEAS 29 OZ. / 30 OZ. | D225: 2410 | E225: 12/29 oz dark red kidney beans | F225: 25.95 | G225: 2.16 | H225: 1.59 | I225: 2.89
A226: 50 | B226: BEANS, LENTILS, PEAS & BAGGED GRAINS | C226: GOYA PREMIUM BEANS & PEAS 29 OZ. / 30 OZ. | D226: 2411 | E226: 12/29 oz pink beans | F226: 25.95 | G226: 2.16 | H226: 1.59 | I226: 2.89
A227: 15 | B227: BEANS, LENTILS, PEAS & BAGGED GRAINS | C227: GOYA PREMIUM BEANS, LENTILS & PEAS 15 OZ. / 15.5 OZ. | D227: 2412 | E227: 24/15.5 oz white | F227: 26.40 | G227: 1.10 | H227: 1.54 | I227: 1.49
A228: 3 | B228: BEANS, LENTILS, PEAS & BAGGED GRAINS | C228: GOYA PREMIUM BEANS & PEAS 10.5 OZ. | D228: 2413 | E228: 24/ white beans | F228: 22.5 | G228: .94 | H228: 1.9 | I228: 1.25
A229: 16 | B229: BEANS, LENTILS, PEAS & BAGGED GRAINS | C229: GOYA PREMIUM BEANS, LENTILS & PEAS 15 OZ. / 15.5 OZ. | D229: 2414 | E229: 24/15.5 oz red cargamanto beans | F229: 33.95 | G229: 1.41 | H229: 1.95 | I229: 1.89
A230: 51 | B230: BEANS, LENTILS, PEAS & BAGGED GRAINS | C230: GOYA PREMIUM BEANS & PEAS 29 OZ. / 30 OZ. | D230: 2415 | E230: 12/29 oz roman beans | F230: 25.95 | G230: 2.16 | H230: 1.59 | I230: 2.89
A231: 17 | B231: BEANS, LENTILS, PEAS & BAGGED GRAINS | C231: GOYA PREMIUM BEANS, LENTILS & PEAS 15 OZ. / 15.5 OZ. | D231: 2416 | E231: 24/15.5 oz roman | F231: 26.40 | G231: 1.10 | H231: 1.54 | I231: 1.49
A232: 52 | B232: BEANS, LENTILS, PEAS & BAGGED GRAINS | C232: GOYA PREMIUM BEANS & PEAS 29 OZ. / 30 OZ. | D232: 2417 | E232: 12/29 oz small reds | F232: 25.95 | G232: 2.16 | H232: 1.59 | I232: 2.89
A233: 18 | B233: BEANS, LENTILS, PEAS & BAGGED GRAINS | C233: GOYA PREMIUM BEANS, LENTILS & PEAS 15 OZ. / 15.5 OZ. | D233: 2418 | E233: 24/15.5 oz white cargamanto beans | F233: 33.95 | G233: 1.41 | H233: 1.95 | I233: 1.89
A234: 53 | B234: BEANS, LENTILS, PEAS & BAGGED GRAINS | C234: GOYA PREMIUM BEANS & PEAS 29 OZ. / 30 OZ. | D234: 2419 | E234: 12/29 oz chick peas | F234: 25.95 | G234: 2.16 | H234: 1.59 | I234: 2.89
A235: 19 | B235: BEANS, LENTILS, PEAS & BAGGED GRAINS | C235: GOYA PREMIUM BEANS, LENTILS & PEAS 15 OZ. / 15.5 OZ. | D235: 2420 | E235: 24/15.5 oz small red | F235: 26.40 | G235: 1.10 | H235: 1.54 | I235: 1.49
A236: 20 | B236: BEANS, LENTILS, PEAS & BAGGED GRAINS | C236: GOYA PREMIUM BEANS, LENTILS & PEAS 15 OZ. / 15.5 OZ. | D236: 2421 | E236: 24/15.5 oz fava beans | F236: 26.40 | G236: 1.10 | H236: 1.54 | I236: 1.49
A237: 21 | B237: BEANS, LENTILS, PEAS & BAGGED GRAINS | C237: GOYA PREMIUM BEANS, LENTILS & PEAS 15 OZ. / 15.5 OZ. | D237: 2422 | E237: 24/15.5 oz chick peas | F237: 26.40 | G237: 1.10 | H237: 1.54 | I237: 1.49
A238: 4 | B238: BEANS, LENTILS, PEAS & BAGGED GRAINS | C238: GOYA PREMIUM BEANS & PEAS 10.5 OZ. | D238: 2423 | E238: 24/ chick peas | F238: 22.50 | G238: .94 | H238: 1.9 | I238: 1.25
A239: 22 | B239: BEANS, LENTILS, PEAS & BAGGED GRAINS | C239: GOYA PREMIUM BEANS, LENTILS & PEAS 15 OZ. / 15.5 OZ. | D239: 2425 | E239: 24/15 oz feijao pedra verde | F239: 33.95 | G239: 1.41 | H239: 2.02 | I239: 1.89
A240: 23 | B240: BEANS, LENTILS, PEAS & BAGGED GRAINS | C240: GOYA PREMIUM BEANS, LENTILS & PEAS 15 OZ. / 15.5 OZ. | D240: 2426 | E240: 24/15.5 oz blackeye peas | F240: 26.40 | G240: 1.10 | H240: 1.54 | I240: 1.49
A241: 5 | B241: BEANS, LENTILS, PEAS & BAGGED GRAINS | C241: GOYA PREMIUM BEANS & PEAS 10.5 OZ. | D241: 2427 | E241: 24/ blackeye | F241: 22.50 | G241: .94 | H241: 1.9 | I241: 1.25
A242: 218 | B242: BEANS, LENTILS, PEAS & BAGGED GRAINS | C242: GOYA DRY BEANS, LENTILS, PEAS & CORN 3 / 4 / 6 LB. | D242: 2428 | E242: 4/6 lb giant white corn | F242: 78.95 | G242: 19.74 | H242: 4.33 | I242: 25.99
A243: 54 | B243: BEANS, LENTILS, PEAS & BAGGED GRAINS | C243: GOYA PREMIUM BEANS & PEAS 29 OZ. / 30 OZ. | D243: 2429 | E243: 12/29 oz blackeye peas | F243: 25.95 | G243: 2.16 | H243: 1.59 | I243: 2.89
A244: 24 | B244: BEANS, LENTILS, PEAS & BAGGED GRAINS | C244: GOYA PREMIUM BEANS, LENTILS & PEAS 15 OZ. / 15.5 OZ. | D244: 2430 | E244: 24/15.5 oz great northern | F244: 26.40 | G244: 1.10 | H244: 1.54 | I244: 1.49
A245: 25 | B245: BEANS, LENTILS, PEAS & BAGGED GRAINS | C245: GOYA PREMIUM BEANS, LENTILS & PEAS 15 OZ. / 15.5 OZ. | D245: 2432 | E245: 24/15.5 oz Dominican red beans | F245: 33.95 | G245: 1.41 | H245: 1.95 | I245: 1.89
A246: 26 | B246: BEANS, LENTILS, PEAS & BAGGED GRAINS | C246: GOYA PREMIUM BEANS, LENTILS & PEAS 15 OZ. / 15.5 OZ. | D246: 2435 | E246: 24/15.5 oz dark red kidney beans | F246: 26.40 | G246: 1.10 | H246: 1.54 | I246: 1.49
A247: 27 | B247: BEANS, LENTILS, PEAS & BAGGED GRAINS | C247: GOYA PREMIUM BEANS, LENTILS & PEAS 15 OZ. / 15.5 OZ. | D247: 2437 | E247: 24/15.5 oz pinto beans | F247: 26.40 | G247: 1.10 | H247: 1.54 | I247: 1.49
A248: 55 | B248: BEANS, LENTILS, PEAS & BAGGED GRAINS | C248: GOYA PREMIUM BEANS & PEAS 29 OZ. / 30 OZ. | D248: 2438 | E248: 12/29 oz. Peruvian/Mayocoba beans | F248: 31.50 | G248: 2.63 | H248: 1.93 | I248: 3.49
A249: 6 | B249: BEANS, LENTILS, PEAS & BAGGED GRAINS | C249: GOYA PREMIUM BEANS & PEAS 10.5 OZ. | D249: 2439 | E249: 24/ pinto | F249: 22.50 | G249: .94 | H249: 1.9 | I249: 1.25
A250: 56 | B250: BEANS, LENTILS, PEAS & BAGGED GRAINS | C250: GOYA PREMIUM BEANS & PEAS 29 OZ. / 30 OZ. | D250: 2442 | E250: 12/29 oz pintos frijoles | F250: 25.95 | G250: 2.16 | H250: 1.59 | I250: 2.89
A251: 28 | B251: BEANS, LENTILS, PEAS & BAGGED GRAINS | C251: GOYA PREMIUM BEANS, LENTILS & PEAS 15 OZ. / 15.5 OZ. | D251: 2443 | E251: 24/15.5 oz butter beans | F251: 38.75 | G251: 1.61 | H251: 2.26 | I251: 2.19
A252: 57 | B252: BEANS, LENTILS, PEAS & BAGGED GRAINS | C252: GOYA PREMIUM BEANS & PEAS 29 OZ. / 30 OZ. | D252: 2444 | E252: 12/29 oz butter beans | F252: 31.50 | G252: 2.63 | H252: 1.93 | I252: 3.49
A253: 29 | B253: BEANS, LENTILS, PEAS & BAGGED GRAINS | C253: GOYA PREMIUM BEANS, LENTILS & PEAS 15 OZ. / 15.5 OZ. | D253: 2446 | E253: 24/15.5 oz cannellini | F253: 33.95 | G253: 1.41 | H253: 1.95 | I253: 1.89
A254: 58 | B254: BEANS, LENTILS, PEAS & BAGGED GRAINS | C254: GOYA PREMIUM BEANS & PEAS 29 OZ. / 30 OZ. | D254: 2449 | E254: 12/29 oz cannellini | F254: 31.50 | G254: 2.63 | H254: 1.93 | I254: 3.49
A255: 30 | B255: BEANS, LENTILS, PEAS & BAGGED GRAINS | C255: GOYA PREMIUM BEANS, LENTILS & PEAS 15 OZ. / 15.5 OZ. | D255: 2451 | E255: 24/15.5 oz canary beans | F255: 33.95 | G255: 1.41 | H255: 1.95 | I255: 1.89
A256: 59 | B256: BEANS, LENTILS, PEAS & BAGGED GRAINS | C256: GOYA PREMIUM BEANS & PEAS 29 OZ. / 30 OZ. | D256: 2452 | E256: 12/29 oz small white beans | F256: 25.95 | G256: 2.16 | H256: 1.59 | I256: 2.89
A257: 71 | B257: BEANS, LENTILS, PEAS & BAGGED GRAINS | C257: GOYA PREMIUM BEANS & PEAS 100.7 OZ. / 110 OZ. | D257: 2453 | E257: 6/110 oz dark kidney | F257: 32.35 | G257: 5.39 | H257: 1.05 | I257: 7.19
A258: 72 | B258: BEANS, LENTILS, PEAS & BAGGED GRAINS | C258: GOYA PREMIUM BEANS & PEAS 100.7 OZ. / 110 OZ. | D258: 2454 | E258: 6/110 oz pinto beans | F258: 32.35 | G258: 5.39 | H258: 1.05 | I258: 7.19
A259: 73 | B259: BEANS, LENTILS, PEAS & BAGGED GRAINS | C259: GOYA PREMIUM BEANS & PEAS 100.7 OZ. / 110 OZ. | D259: 2455 | E259: 6/110 oz pink beans | F259: 32.35 | G259: 5.39 | H259: 1.05 | I259: 7.19
A260: 31 | B260: BEANS, LENTILS, PEAS & BAGGED GRAINS | C260: GOYA PREMIUM BEANS, LENTILS & PEAS 15 OZ. / 15.5 OZ. | D260: 2456 | E260: 24/15.5 oz lentils | F260: 26.40 | G260: 1.10 | H260: 1.54 | I260: 1.49
A261: 74 | B261: BEANS, LENTILS, PEAS & BAGGED GRAINS | C261: GOYA PREMIUM BEANS & PEAS 100.7 OZ. / 110 OZ. | D261: 2457 | E261: 6/110 oz red kidney beans | F261: 32.35 | G261: 5.39 | H261: 1.05 | I261: 7.19
... A268: 35 | B268: BEANS, LENTILS, PEAS & BAGGED GRAINS | C268: GOYA PREMIUM BEANS, LENTILS & PEAS 15 OZ. / 15.5 OZ. | D268: 2466 | E268: 24/15.5 oz black beans | F268: 26.40 | G268: 1.10 | H268: 1.54 | I268: 1.49
A269: 7 | B269: BEANS, LENTILS, PEAS & BAGGED GRAINS | C269: GOYA PREMIUM BEANS & PEAS 10.5 OZ. | D269: 2467 | E269: 24/ green peas | F269: 22.50 | G269: .94 | H269: 1.9 | I269: 1.25
A270: 8 | B270: BEANS, LENTILS, PEAS & BAGGED GRAINS | C270: GOYA PREMIUM BEANS & PEAS 10.5 OZ. | D270: 2469 | E270: 24/ black beans | F270: 22.50 | G270: .94 | H270: 1.9 | I270: 1.25
A271: 175 | B271: BEANS, LENTILS, PEAS & BAGGED GRAINS | C271: GOYA BEANS, LENTILS, PEAS & DRY GRAINS 16 OZ. | D271: 2470 | E271: 24/ small white | F271: 40.95 | G271: 1.71 | H271: 2.29 | I271: 2.29
A272: 176 | B272: BEANS, LENTILS, PEAS & BAGGED GRAINS | C272: GOYA BEANS, LENTILS, PEAS & DRY GRAINS 16 OZ. | D272: 2471 | E272: 24/ red kidney | F272: 35.95 | G272: 1.50 | H272: 1.99 | I272: 1.99
A273: 177 | B273: BEANS, LENTILS, PEAS & BAGGED GRAINS | C273: GOYA BEANS, LENTILS, PEAS & DRY GRAINS 16 OZ. | D273: 2472 | E273: 24/ pinto | F273: 30.50 | G273: 1.27 | H273: 1.69 | I273: 1.69
A274: 178 | B274: BEANS, LENTILS, PEAS & BAGGED GRAINS | C274: GOYA BEANS, LENTILS, PEAS & DRY GRAINS 16 OZ. | D274: 2473 | E274: 24/ baby lima | F274: 43.50 | G274: 1.81 | H274: 2.39 | I274: 2.39
A275: 179 | B275: BEANS, LENTILS, PEAS & BAGGED GRAINS | C275: GOYA BEANS, LENTILS, PEAS & DRY GRAINS 16 OZ. | D275: 2474 | E275: 24/ blackeye peas | F275: 47.95 | G275: 2.00 | H275: 2.69 | I275: 2.69
A276: 180 | B276: BEANS, LENTILS, PEAS & BAGGED GRAINS | C276: GOYA BEANS, LENTILS, PEAS & DRY GRAINS 16 OZ. | D276: 2475 | E276: 24/ whole green peas | F276: 21.95 | G276: 0.91 | H276: 1.19 | I276: 1.19
A277: 181 | B277: BEANS, LENTILS, PEAS & BAGGED GRAINS | C277: GOYA BEANS, LENTILS, PEAS & DRY GRAINS 16 OZ. | D277: 2476 | E277: 24/ lentils | F277: 33.95 | G277: 1.41 | H277: 1.89 | I277: 1.89
A278: 182 | B278: BEANS, LENTILS, PEAS & BAGGED GRAINS | C278: GOYA BEANS, LENTILS, PEAS & DRY GRAINS 16 OZ. | D278: 2477 | E278: 24/ pink beans | F278: 37.95 | G278: 1.58 | H278: 2.09 | I278: 2.09
A279: 183 | B279: BEANS, LENTILS, PEAS & BAGGED GRAINS | C279: GOYA BEANS, LENTILS, PEAS & DRY GRAINS 16 OZ. | D279: 2478 | E279: 24/ chick peas | F279: 43.50 | G279: 1.81 | H279: 2.39 | I279: 2.39
A280: 184 | B280: BEANS, LENTILS, PEAS & BAGGED GRAINS | C280: GOYA BEANS, LENTILS, PEAS & DRY GRAINS 16 OZ. | D280: 2479 | E280: 24/ black beans | F280: 32.50 | G280: 1.35 | H280: 1.79 | I280: 1.79
A281: 185 | B281: BEANS, LENTILS, PEAS & BAGGED GRAINS | C281: GOYA BEANS, LENTILS, PEAS & DRY GRAINS 16 OZ. | D281: 2480 | E281: 24/ lb. Dominican red beans | F281: 60.95 | G281: 2.54 | H281: 3.39 | I281: 3.39
A282: 186 | B282: BEANS, LENTILS, PEAS & BAGGED GRAINS | C282: GOYA BEANS, LENTILS, PEAS & DRY GRAINS 16 OZ. | D282: 2481 | E282: 24/ large lima | F282: 59.95 | G282: 2.50 | H282: 3.29 | I282: 3.29
A283: 187 | B283: BEANS, LENTILS, PEAS & BAGGED GRAINS | C283: GOYA BEANS, LENTILS, PEAS & DRY GRAINS 16 OZ. | D283: 2482 | E283: 24/ pigeon peas | F283: 45.95 | G283: 1.91 | H283: 2.59 | I283: 2.59
A284: 188 | B284: BEANS, LENTILS, PEAS & BAGGED GRAINS | C284: GOYA BEANS, LENTILS, PEAS & DRY GRAINS 16 OZ. | D284: 2483 | E284: 24/ roman beans | F284: 39.50 | G284: 1.65 | H284: 2.19 | I284: 2.19
A285: 189 | B285: BEANS, LENTILS, PEAS & BAGGED GRAINS | C285: GOYA BEANS, LENTILS, PEAS & DRY GRAINS 16 OZ. | D285: 2484 | E285: 24/ large fava beans | F285: 41.50 | G285: 1.73 | H285: 2.29 | I285: 2.29
A286: 190 | B286: BEANS, LENTILS, PEAS & BAGGED GRAINS | C286: GOYA BEANS, LENTILS, PEAS & DRY GRAINS 16 OZ. | D286: 2485 | E286: 24/ great northern | F286: 34.95 | G286: 1.46 | H286: 1.95 | I286: 1.95
A287: 191 | B287: BEANS, LENTILS, PEAS & BAGGED GRAINS | C287: GOYA BEANS, LENTILS, PEAS & DRY GRAINS 16 OZ. | D287: 2486 | E287: 24/ small reds | F287: 33.95 | G287: 1.41 | H287: 1.89 | I287: 1.89
A288: 192 | B288: BEANS, LENTILS, PEAS & BAGGED GRAINS | C288: GOYA BEANS, LENTILS, PEAS & DRY GRAINS 16 OZ. | D288: 2487 | E288: 24/ green split peas | F288: 24.95 | G288: 1.04 | H288: 1.39 | I288: 1.39
... A326: 1675 | B326: VEGETABLES | C326: GOYA CAN/ VEGETABLES | D326: 2531 | E326: 24/15 oz tender sweet peas | F326: 29.95 | G326: 1.25 | H326: 1.80 | I326: 1.69
A327: 1676 | B327: VEGETABLES | C327: GOYA CAN/ VEGETABLES | D327: 2533 | E327: 24/8.5 oz tender sweet peas | F327: 21.75 | G327: 0.91 | H327: 2.24 | I327: 1.19
A328: 214 | B328: BEANS, LENTILS, PEAS & BAGGED GRAINS | C328: GOYA BEANS, LENTILS, PEAS & DRY GRAINS 16 OZ. | D328: 2534 | E328: 24/ adzuki beans | F328: 46.65 | G328: 1.94 | H328: 2.59 | I328: 2.59
A329: 1677 | B329: VEGETABLES | C329: GOYA CAN/ VEGETABLES | D329: 2535 | E329: 24/14.5 oz french style green beans | F329: 27.50 | G329: 1.15 | H329: 1.64 | I329: 1.49
A330: 1678 | B330: VEGETABLES | C330: GOYA CAN/ VEGETABLES | D330: 2536 | E330: 24/8 oz french style green beans | F330: 20.95 | G330: 0.87 | H330: 2.38 | I330: 1.19
A331: 1679 | B331: VEGETABLES | C331: GOYA CAN/ VEGETABLES | D331: 2537 | E331: 24/8 oz cut green beans | F331: 20.95 | G331: 0.87 | H331: 2.38 | I331: 1.19
...

Sheet Sheet3
A1: 2706 | B1: Rice Mix Shipper (2) 48/7oz
A2: 4162 | B2: Parchment Paper
A3: 4165 | B3: Cotton Twine 2.6oz 800Ft
A4: 6438 | B4: Goya Saltine Crackers Red Tin
A5: 8801 | B5: Alpina Yogo Yogo Peach Drink
A6: 8802 | B6: Alpina Yogo Yogo Strawberry
A7: 4334 | B7: Goya Aloe Original Sugar Free
A8: 4335 | B8: Goya Aloe Original Organic
A9: 9505 | B9: Breadfruit Chunks
A10: 9411 | B10: Masa de Guineo
A11: 4536 | B11: Goya Queso Fresco
A12: 4537 | B12: Goya Queso Quesadilla
... A48: 5026 | B48: Goya 4-Pk Maria Cookies QT Plt
A49: 4368 | B49: Goya Chickpea Puff Chile Limon
A50: 4369 | B50: Chickpea Puffs Elote Mex Corn
A51: 4370 | B51: Goya Chickpea Puffs Churros
A52: 4374 | B52: Goya Chickpea Puffs Chile Limon
A53: 4408 | B53: Chickpea Puffs Elote Mex Corn
A54: 4409 | B54: Chickpea Puffs Churros
A55: 9514 | B55: Cheese and Guava Flan
A56: 3686 | B56: Goya Condensed Milk Easy Open
A57: 5990 | B57: Organic Thai Hom Mali Rice 2Lb
A58: 5991 | B58: Organic Thai Hom Mali Rice 5Lb
A59: 4512 | B59: Ducal Refried Red Bean DP 40oz
A60: 5993 | B60: Vegan Mexican Rice Mix 7oz
A61: 5963 | B61: Goya Yellow Corn Masarepa 25Lb.
